[ {
  "from" : "VCE",
  "to" : "CDG",
  "airlineDesignator" : "AF",
  "flightNumber" : "1327",
  "departureDate" : [ 2022, 1, 1 ],
  "departureTime" : [ 6, 0 ],
  "arrivalTime" : [ 7, 50 ],
  "travelTimeMinutes" : 110,
  "aircraft" : "319"
}, {
  "from" : "MAD",
  "to" : "CDG",
  "airlineDesignator" : "AF",
  "flightNumber" : "1401",
  "departureDate" : [ 2022, 1, 1 ],
  "departureTime" : [ 6, 0 ],
  "arrivalTime" : [ 8, 5 ],
  "travelTimeMinutes" : 125,
  "aircraft" : "321"
}, {
  "from" : "TRN",
  "to" : "CDG",
  "airlineDesignator" : "AF",
  "flightNumber" : "1503*",
  "departureDate" : [ 2022, 1, 1 ],
  "departureTime" : [ 6, 0 ],
  "arrivalTime" : [ 7, 20 ],
  "travelTimeMinutes" : 80,
  "aircraft" : "E90"
}, {
  "from" : "CDG",
  "to" : "LYS",
  "airlineDesignator" : "AF",
  "flightNumber" : "7651",
  "departureDate" : [ 2022, 1, 1 ],
  "departureTime" : [ 6, 0 ],
  "arrivalTime" : [ 7, 10 ],
  "travelTimeMinutes" : 70,
  "aircraft" : "321"
}, {
  "from" : "LYS",
  "to" : "CDG",
  "airlineDesignator" : "AF",
  "flightNumber" : "7651",
  "departureDate" : [ 2022, 1, 1 ],
  "departureTime" : [ 6, 0 ],
  "arrivalTime" : [ 7, 10 ],
  "travelTimeMinutes" : 70,
  "aircraft" : "321"
}, {
  "from" : "AGP",
  "to" : "CDG",
  "airlineDesignator" : "AF",
  "flightNumber" : "9441",
  "departureDate" : [ 2022, 1, 1 ],
  "departureTime" : [ 6, 0 ],
  "arrivalTime" : [ 8, 40 ],
  "travelTimeMinutes" : 160,
  "aircraft" : "319"
}, {
  "from" : "CJS",
  "to" : "MEX",
  "airlineDesignator" : "AM",
  "flightNumber" : "112",
  "departureDate" : [ 2022, 1, 1 ],
  "departureTime" : [ 6, 0 ],
  "arrivalTime" : [ 9, 40 ],
  "travelTimeMinutes" : 160,
  "aircraft" : "7M7"
}, {
  "from" : "CUL",
  "to" : "MEX",
  "airlineDesignator" : "AM",
  "flightNumber" : "161",
  "departureDate" : [ 2022, 1, 1 ],
  "departureTime" : [ 6, 0 ],
  "arrivalTime" : [ 9, 5 ],
  "travelTimeMinutes" : 125,
  "aircraft" : "E90"
}, {
  "from" : "ZCL",
  "to" : "MEX",
  "airlineDesignator" : "AM",
  "flightNumber" : "2649",
  "departureDate" : [ 2022, 1, 1 ],
  "departureTime" : [ 6, 0 ],
  "arrivalTime" : [ 7, 20 ],
  "travelTimeMinutes" : 80,
  "aircraft" : "E90"
}, {
  "from" : "VSA",
  "to" : "IAH",
  "airlineDesignator" : "AM",
  "flightNumber" : "472",
  "departureDate" : [ 2022, 1, 1 ],
  "departureTime" : [ 6, 0 ],
  "arrivalTime" : [ 13, 14 ],
  "travelTimeMinutes" : 434,
  "aircraft" : "7S8"
}, {
  "from" : "HMO",
  "to" : "MEX",
  "airlineDesignator" : "AM",
  "flightNumber" : "701",
  "departureDate" : [ 2022, 1, 1 ],
  "departureTime" : [ 6, 0 ],
  "arrivalTime" : [ 10, 40 ],
  "travelTimeMinutes" : 160,
  "aircraft" : "7M7"
}, {
  "from" : "CTA",
  "to" : "FCO",
  "airlineDesignator" : "AZ",
  "flightNumber" : "1722*",
  "departureDate" : [ 2022, 1, 1 ],
  "departureTime" : [ 6, 0 ],
  "arrivalTime" : [ 7, 25 ],
  "travelTimeMinutes" : 85,
  "aircraft" : "319"
}, {
  "from" : "CTA",
  "to" : "LIN",
  "airlineDesignator" : "AZ",
  "flightNumber" : "1742*",
  "departureDate" : [ 2022, 1, 1 ],
  "departureTime" : [ 6, 0 ],
  "arrivalTime" : [ 7, 50 ],
  "travelTimeMinutes" : 110,
  "aircraft" : "32S"
}, {
  "from" : "PMO",
  "to" : "LIN",
  "airlineDesignator" : "AZ",
  "flightNumber" : "1768*",
  "departureDate" : [ 2022, 1, 1 ],
  "departureTime" : [ 6, 0 ],
  "arrivalTime" : [ 7, 35 ],
  "travelTimeMinutes" : 95,
  "aircraft" : "32S"
}, {
  "from" : "MAD",
  "to" : "AMS",
  "airlineDesignator" : "CI",
  "flightNumber" : "9478*",
  "departureDate" : [ 2022, 1, 1 ],
  "departureTime" : [ 6, 0 ],
  "arrivalTime" : [ 8, 25 ],
  "travelTimeMinutes" : 145,
  "aircraft" : "73H"
}, {
  "from" : "CHC",
  "to" : "SYD",
  "airlineDesignator" : "CI",
  "flightNumber" : "9988*",
  "departureDate" : [ 2022, 1, 1 ],
  "departureTime" : [ 6, 0 ],
  "arrivalTime" : [ 7, 35 ],
  "travelTimeMinutes" : 215,
  "aircraft" : "73H"
}, {
  "from" : "CVG",
  "to" : "ATL",
  "airlineDesignator" : "DL",
  "flightNumber" : "1349",
  "departureDate" : [ 2022, 1, 1 ],
  "departureTime" : [ 6, 0 ],
  "arrivalTime" : [ 7, 27 ],
  "travelTimeMinutes" : 87,
  "aircraft" : "739"
}, {
  "from" : "BZN",
  "to" : "MSP",
  "airlineDesignator" : "DL",
  "flightNumber" : "2344",
  "departureDate" : [ 2022, 1, 1 ],
  "departureTime" : [ 6, 0 ],
  "arrivalTime" : [ 9, 13 ],
  "travelTimeMinutes" : 133,
  "aircraft" : "321"
}, {
  "from" : "DCA",
  "to" : "DTW",
  "airlineDesignator" : "DL",
  "flightNumber" : "2885",
  "departureDate" : [ 2022, 1, 1 ],
  "departureTime" : [ 6, 0 ],
  "arrivalTime" : [ 7, 32 ],
  "travelTimeMinutes" : 92,
  "aircraft" : "320"
}, {
  "from" : "MSO",
  "to" : "SLC",
  "airlineDesignator" : "DL",
  "flightNumber" : "3610",
  "departureDate" : [ 2022, 1, 1 ],
  "departureTime" : [ 6, 0 ],
  "arrivalTime" : [ 7, 30 ],
  "travelTimeMinutes" : 90,
  "aircraft" : "E7W"
}, {
  "from" : "MEM",
  "to" : "LGA",
  "airlineDesignator" : "DL",
  "flightNumber" : "5050",
  "departureDate" : [ 2022, 1, 1 ],
  "departureTime" : [ 6, 0 ],
  "arrivalTime" : [ 9, 39 ],
  "travelTimeMinutes" : 159,
  "aircraft" : "CR9"
}, {
  "from" : "SFO",
  "to" : "JFK",
  "airlineDesignator" : "DL",
  "flightNumber" : "561",
  "departureDate" : [ 2022, 1, 1 ],
  "departureTime" : [ 6, 0 ],
  "arrivalTime" : [ 14, 40 ],
  "travelTimeMinutes" : 340,
  "aircraft" : "76W"
}, {
  "from" : "DCA",
  "to" : "LGA",
  "airlineDesignator" : "DL",
  "flightNumber" : "5629",
  "departureDate" : [ 2022, 1, 1 ],
  "departureTime" : [ 6, 0 ],
  "arrivalTime" : [ 7, 10 ],
  "travelTimeMinutes" : 70,
  "aircraft" : "E75"
}, {
  "from" : "YVR",
  "to" : "YYC",
  "airlineDesignator" : "DL",
  "flightNumber" : "6901*",
  "departureDate" : [ 2022, 1, 1 ],
  "departureTime" : [ 6, 0 ],
  "arrivalTime" : [ 8, 23 ],
  "travelTimeMinutes" : 83,
  "aircraft" : "73H"
}, {
  "from" : "YCD",
  "to" : "YYC",
  "airlineDesignator" : "DL",
  "flightNumber" : "7011*",
  "departureDate" : [ 2022, 1, 1 ],
  "departureTime" : [ 6, 0 ],
  "arrivalTime" : [ 8, 40 ],
  "travelTimeMinutes" : 100,
  "aircraft" : "DH4"
}, {
  "from" : "YQU",
  "to" : "YYC",
  "airlineDesignator" : "DL",
  "flightNumber" : "7020*",
  "departureDate" : [ 2022, 1, 1 ],
  "departureTime" : [ 6, 0 ],
  "arrivalTime" : [ 7, 25 ],
  "travelTimeMinutes" : 85,
  "aircraft" : "DH4"
}, {
  "from" : "YMM",
  "to" : "YYC",
  "airlineDesignator" : "DL",
  "flightNumber" : "7038*",
  "departureDate" : [ 2022, 1, 1 ],
  "departureTime" : [ 6, 0 ],
  "arrivalTime" : [ 7, 42 ],
  "travelTimeMinutes" : 102,
  "aircraft" : "DH4"
}, {
  "from" : "YYJ",
  "to" : "YYC",
  "airlineDesignator" : "DL",
  "flightNumber" : "7269*",
  "departureDate" : [ 2022, 1, 1 ],
  "departureTime" : [ 6, 0 ],
  "arrivalTime" : [ 8, 23 ],
  "travelTimeMinutes" : 83,
  "aircraft" : "73H"
}, {
  "from" : "PEN",
  "to" : "KUL",
  "airlineDesignator" : "GA",
  "flightNumber" : "9390*",
  "departureDate" : [ 2022, 1, 1 ],
  "departureTime" : [ 6, 0 ],
  "arrivalTime" : [ 7, 5 ],
  "travelTimeMinutes" : 65,
  "aircraft" : "738"
}, {
  "from" : "CPH",
  "to" : "AMS",
  "airlineDesignator" : "KL",
  "flightNumber" : "1124",
  "departureDate" : [ 2022, 1, 1 ],
  "departureTime" : [ 6, 0 ],
  "arrivalTime" : [ 7, 25 ],
  "travelTimeMinutes" : 85,
  "aircraft" : "73H"
}, {
  "from" : "TRD",
  "to" : "AMS",
  "airlineDesignator" : "KL",
  "flightNumber" : "1172",
  "departureDate" : [ 2022, 1, 1 ],
  "departureTime" : [ 6, 0 ],
  "arrivalTime" : [ 8, 15 ],
  "travelTimeMinutes" : 135,
  "aircraft" : "E90"
}, {
  "from" : "EDI",
  "to" : "AMS",
  "airlineDesignator" : "KL",
  "flightNumber" : "1276",
  "departureDate" : [ 2022, 1, 1 ],
  "departureTime" : [ 6, 0 ],
  "arrivalTime" : [ 8, 35 ],
  "travelTimeMinutes" : 95,
  "aircraft" : "73H"
}, {
  "from" : "BLL",
  "to" : "AMS",
  "airlineDesignator" : "KL",
  "flightNumber" : "1340",
  "departureDate" : [ 2022, 1, 1 ],
  "departureTime" : [ 6, 0 ],
  "arrivalTime" : [ 7, 10 ],
  "travelTimeMinutes" : 70,
  "aircraft" : "73H"
}, {
  "from" : "BHX",
  "to" : "AMS",
  "airlineDesignator" : "KL",
  "flightNumber" : "1420",
  "departureDate" : [ 2022, 1, 1 ],
  "departureTime" : [ 6, 0 ],
  "arrivalTime" : [ 8, 20 ],
  "travelTimeMinutes" : 80,
  "aircraft" : "73H"
}, {
  "from" : "BLQ",
  "to" : "AMS",
  "airlineDesignator" : "KL",
  "flightNumber" : "1582",
  "departureDate" : [ 2022, 1, 1 ],
  "departureTime" : [ 6, 0 ],
  "arrivalTime" : [ 7, 55 ],
  "travelTimeMinutes" : 115,
  "aircraft" : "E90"
}, {
  "from" : "VCE",
  "to" : "AMS",
  "airlineDesignator" : "KL",
  "flightNumber" : "1650",
  "departureDate" : [ 2022, 1, 1 ],
  "departureTime" : [ 6, 0 ],
  "arrivalTime" : [ 7, 50 ],
  "travelTimeMinutes" : 110,
  "aircraft" : "73W"
}, {
  "from" : "MAD",
  "to" : "AMS",
  "airlineDesignator" : "KL",
  "flightNumber" : "1698",
  "departureDate" : [ 2022, 1, 1 ],
  "departureTime" : [ 6, 0 ],
  "arrivalTime" : [ 8, 25 ],
  "travelTimeMinutes" : 145,
  "aircraft" : "73H"
}, {
  "from" : "STR",
  "to" : "AMS",
  "airlineDesignator" : "KL",
  "flightNumber" : "1866",
  "departureDate" : [ 2022, 1, 1 ],
  "departureTime" : [ 6, 0 ],
  "arrivalTime" : [ 7, 25 ],
  "travelTimeMinutes" : 85,
  "aircraft" : "E90"
}, {
  "from" : "HAJ",
  "to" : "AMS",
  "airlineDesignator" : "KL",
  "flightNumber" : "1900",
  "departureDate" : [ 2022, 1, 1 ],
  "departureTime" : [ 6, 0 ],
  "arrivalTime" : [ 7, 0 ],
  "travelTimeMinutes" : 60,
  "aircraft" : "E75"
}, {
  "from" : "TRN",
  "to" : "CDG",
  "airlineDesignator" : "KQ",
  "flightNumber" : "3809*",
  "departureDate" : [ 2022, 1, 1 ],
  "departureTime" : [ 6, 0 ],
  "arrivalTime" : [ 7, 20 ],
  "travelTimeMinutes" : 80,
  "aircraft" : "E90"
}, {
  "from" : "AKL",
  "to" : "SYD",
  "airlineDesignator" : "MU",
  "flightNumber" : "4336*",
  "departureDate" : [ 2022, 1, 1 ],
  "departureTime" : [ 6, 0 ],
  "arrivalTime" : [ 7, 40 ],
  "travelTimeMinutes" : 220,
  "aircraft" : "73H"
}, {
  "from" : "AKL",
  "to" : "MEL",
  "airlineDesignator" : "MU",
  "flightNumber" : "4338*",
  "departureDate" : [ 2022, 1, 1 ],
  "departureTime" : [ 6, 0 ],
  "arrivalTime" : [ 8, 15 ],
  "travelTimeMinutes" : 255,
  "aircraft" : "73H"
}, {
  "from" : "CHC",
  "to" : "SYD",
  "airlineDesignator" : "MU",
  "flightNumber" : "4342*",
  "departureDate" : [ 2022, 1, 1 ],
  "departureTime" : [ 6, 0 ],
  "arrivalTime" : [ 7, 35 ],
  "travelTimeMinutes" : 215,
  "aircraft" : "73H"
}, {
  "from" : "PRG",
  "to" : "BOJ",
  "airlineDesignator" : "OK",
  "flightNumber" : "4852*",
  "departureDate" : [ 2022, 1, 1 ],
  "departureTime" : [ 6, 0 ],
  "arrivalTime" : [ 9, 5 ],
  "travelTimeMinutes" : 125,
  "aircraft" : "738"
}, {
  "from" : "ARH",
  "to" : "SVO",
  "airlineDesignator" : "SU",
  "flightNumber" : "1335",
  "departureDate" : [ 2022, 1, 1 ],
  "departureTime" : [ 6, 0 ],
  "arrivalTime" : [ 7, 55 ],
  "travelTimeMinutes" : 115,
  "aircraft" : "32A"
}, {
  "from" : "MSQ",
  "to" : "SVO",
  "airlineDesignator" : "SU",
  "flightNumber" : "1835",
  "departureDate" : [ 2022, 1, 1 ],
  "departureTime" : [ 6, 0 ],
  "arrivalTime" : [ 7, 35 ],
  "travelTimeMinutes" : 95,
  "aircraft" : "320"
}, {
  "from" : "SVO",
  "to" : "LED",
  "airlineDesignator" : "SU",
  "flightNumber" : "2",
  "departureDate" : [ 2022, 1, 1 ],
  "departureTime" : [ 6, 0 ],
  "arrivalTime" : [ 7, 25 ],
  "travelTimeMinutes" : 85,
  "aircraft" : "320"
}, {
  "from" : "SVO",
  "to" : "GOJ",
  "airlineDesignator" : "SU",
  "flightNumber" : "6253",
  "departureDate" : [ 2022, 1, 1 ],
  "departureTime" : [ 6, 0 ],
  "arrivalTime" : [ 7, 20 ],
  "travelTimeMinutes" : 80,
  "aircraft" : "SU9"
}, {
  "from" : "RUH",
  "to" : "JED",
  "airlineDesignator" : "SV",
  "flightNumber" : "1019",
  "departureDate" : [ 2022, 1, 1 ],
  "departureTime" : [ 6, 0 ],
  "arrivalTime" : [ 7, 45 ],
  "travelTimeMinutes" : 105,
  "aircraft" : "320"
}, {
  "from" : "JED",
  "to" : "BAH",
  "airlineDesignator" : "SV",
  "flightNumber" : "6504*",
  "departureDate" : [ 2022, 1, 1 ],
  "departureTime" : [ 6, 0 ],
  "arrivalTime" : [ 8, 10 ],
  "travelTimeMinutes" : 130,
  "aircraft" : "320"
}, {
  "from" : "CTA",
  "to" : "FCO",
  "airlineDesignator" : "SV",
  "flightNumber" : "6718*",
  "departureDate" : [ 2022, 1, 1 ],
  "departureTime" : [ 6, 0 ],
  "arrivalTime" : [ 7, 25 ],
  "travelTimeMinutes" : 85,
  "aircraft" : "319"
}, {
  "from" : "SGN",
  "to" : "HUI",
  "airlineDesignator" : "VN",
  "flightNumber" : "1370",
  "departureDate" : [ 2022, 1, 1 ],
  "departureTime" : [ 6, 0 ],
  "arrivalTime" : [ 7, 30 ],
  "travelTimeMinutes" : 90,
  "aircraft" : "321"
}, {
  "from" : "SGN",
  "to" : "HAN",
  "airlineDesignator" : "VN",
  "flightNumber" : "206",
  "departureDate" : [ 2022, 1, 1 ],
  "departureTime" : [ 6, 0 ],
  "arrivalTime" : [ 8, 10 ],
  "travelTimeMinutes" : 130,
  "aircraft" : "359"
}, {
  "from" : "MEX",
  "to" : "GDL",
  "airlineDesignator" : "AM",
  "flightNumber" : "200",
  "departureDate" : [ 2022, 1, 1 ],
  "departureTime" : [ 6, 1 ],
  "arrivalTime" : [ 7, 31 ],
  "travelTimeMinutes" : 90,
  "aircraft" : "7S8"
}, {
  "from" : "MZT",
  "to" : "MEX",
  "airlineDesignator" : "AM",
  "flightNumber" : "351",
  "departureDate" : [ 2022, 1, 1 ],
  "departureTime" : [ 6, 1 ],
  "arrivalTime" : [ 8, 55 ],
  "travelTimeMinutes" : 114,
  "aircraft" : "E90"
}, {
  "from" : "CUN",
  "to" : "MEX",
  "airlineDesignator" : "AM",
  "flightNumber" : "501",
  "departureDate" : [ 2022, 1, 1 ],
  "departureTime" : [ 6, 1 ],
  "arrivalTime" : [ 8, 35 ],
  "travelTimeMinutes" : 154,
  "aircraft" : "7M8"
}, {
  "from" : "BJX",
  "to" : "MEX",
  "airlineDesignator" : "AM",
  "flightNumber" : "133",
  "departureDate" : [ 2022, 1, 1 ],
  "departureTime" : [ 6, 3 ],
  "arrivalTime" : [ 7, 10 ],
  "travelTimeMinutes" : 67,
  "aircraft" : "E90"
}, {
  "from" : "MTY",
  "to" : "MEX",
  "airlineDesignator" : "AM",
  "flightNumber" : "901",
  "departureDate" : [ 2022, 1, 1 ],
  "departureTime" : [ 6, 3 ],
  "arrivalTime" : [ 7, 50 ],
  "travelTimeMinutes" : 107,
  "aircraft" : "7S8"
}, {
  "from" : "WAW",
  "to" : "CDG",
  "airlineDesignator" : "AF",
  "flightNumber" : "1247",
  "departureDate" : [ 2022, 1, 1 ],
  "departureTime" : [ 6, 5 ],
  "arrivalTime" : [ 8, 35 ],
  "travelTimeMinutes" : 150,
  "aircraft" : "320"
}, {
  "from" : "ARN",
  "to" : "CDG",
  "airlineDesignator" : "AF",
  "flightNumber" : "1463",
  "departureDate" : [ 2022, 1, 1 ],
  "departureTime" : [ 6, 5 ],
  "arrivalTime" : [ 8, 50 ],
  "travelTimeMinutes" : 165,
  "aircraft" : "320"
}, {
  "from" : "TLS",
  "to" : "CDG",
  "airlineDesignator" : "AF",
  "flightNumber" : "7529",
  "departureDate" : [ 2022, 1, 1 ],
  "departureTime" : [ 6, 5 ],
  "arrivalTime" : [ 7, 35 ],
  "travelTimeMinutes" : 90,
  "aircraft" : "321"
}, {
  "from" : "BOD",
  "to" : "CDG",
  "airlineDesignator" : "AF",
  "flightNumber" : "7621",
  "departureDate" : [ 2022, 1, 1 ],
  "departureTime" : [ 6, 5 ],
  "arrivalTime" : [ 7, 30 ],
  "travelTimeMinutes" : 85,
  "aircraft" : "321"
}, {
  "from" : "CDG",
  "to" : "BOD",
  "airlineDesignator" : "AF",
  "flightNumber" : "7621",
  "departureDate" : [ 2022, 1, 1 ],
  "departureTime" : [ 6, 5 ],
  "arrivalTime" : [ 7, 30 ],
  "travelTimeMinutes" : 85,
  "aircraft" : "321"
}, {
  "from" : "CDG",
  "to" : "NTE",
  "airlineDesignator" : "AF",
  "flightNumber" : "7721",
  "departureDate" : [ 2022, 1, 1 ],
  "departureTime" : [ 6, 5 ],
  "arrivalTime" : [ 7, 10 ],
  "travelTimeMinutes" : 65,
  "aircraft" : "319"
}, {
  "from" : "NTE",
  "to" : "CDG",
  "airlineDesignator" : "AF",
  "flightNumber" : "7721",
  "departureDate" : [ 2022, 1, 1 ],
  "departureTime" : [ 6, 5 ],
  "arrivalTime" : [ 7, 10 ],
  "travelTimeMinutes" : 65,
  "aircraft" : "319"
}, {
  "from" : "AGU",
  "to" : "MEX",
  "airlineDesignator" : "AM",
  "flightNumber" : "2631",
  "departureDate" : [ 2022, 1, 1 ],
  "departureTime" : [ 6, 5 ],
  "arrivalTime" : [ 7, 15 ],
  "travelTimeMinutes" : 70,
  "aircraft" : "E90"
}, {
  "from" : "PRG",
  "to" : "AMS",
  "airlineDesignator" : "CI",
  "flightNumber" : "9488*",
  "departureDate" : [ 2022, 1, 1 ],
  "departureTime" : [ 6, 5 ],
  "arrivalTime" : [ 7, 35 ],
  "travelTimeMinutes" : 90,
  "aircraft" : "73H"
}, {
  "from" : "BOS",
  "to" : "MSP",
  "airlineDesignator" : "DL",
  "flightNumber" : "963",
  "departureDate" : [ 2022, 1, 1 ],
  "departureTime" : [ 6, 5 ],
  "arrivalTime" : [ 8, 20 ],
  "travelTimeMinutes" : 195,
  "aircraft" : "321"
}, {
  "from" : "LPI",
  "to" : "AMS",
  "airlineDesignator" : "KL",
  "flightNumber" : "1178",
  "departureDate" : [ 2022, 1, 1 ],
  "departureTime" : [ 6, 5 ],
  "arrivalTime" : [ 7, 50 ],
  "travelTimeMinutes" : 105,
  "aircraft" : "E90"
}, {
  "from" : "BGO",
  "to" : "AMS",
  "airlineDesignator" : "KL",
  "flightNumber" : "1184",
  "departureDate" : [ 2022, 1, 1 ],
  "departureTime" : [ 6, 5 ],
  "arrivalTime" : [ 7, 45 ],
  "travelTimeMinutes" : 100,
  "aircraft" : "73H"
}, {
  "from" : "PRG",
  "to" : "AMS",
  "airlineDesignator" : "KL",
  "flightNumber" : "1350",
  "departureDate" : [ 2022, 1, 1 ],
  "departureTime" : [ 6, 5 ],
  "arrivalTime" : [ 7, 35 ],
  "travelTimeMinutes" : 90,
  "aircraft" : "73H"
}, {
  "from" : "NWI",
  "to" : "AMS",
  "airlineDesignator" : "KL",
  "flightNumber" : "1514",
  "departureDate" : [ 2022, 1, 1 ],
  "departureTime" : [ 6, 5 ],
  "arrivalTime" : [ 8, 0 ],
  "travelTimeMinutes" : 55,
  "aircraft" : "E75"
}, {
  "from" : "CDG",
  "to" : "NTE",
  "airlineDesignator" : "KL",
  "flightNumber" : "2309*",
  "departureDate" : [ 2022, 1, 1 ],
  "departureTime" : [ 6, 5 ],
  "arrivalTime" : [ 7, 10 ],
  "travelTimeMinutes" : 65,
  "aircraft" : "319"
}, {
  "from" : "NTE",
  "to" : "CDG",
  "airlineDesignator" : "KL",
  "flightNumber" : "2309*",
  "departureDate" : [ 2022, 1, 1 ],
  "departureTime" : [ 6, 5 ],
  "arrivalTime" : [ 7, 10 ],
  "travelTimeMinutes" : 65,
  "aircraft" : "319"
}, {
  "from" : "PVG",
  "to" : "JMU",
  "airlineDesignator" : "MU",
  "flightNumber" : "5535",
  "departureDate" : [ 2022, 1, 1 ],
  "departureTime" : [ 6, 5 ],
  "arrivalTime" : [ 11, 20 ],
  "travelTimeMinutes" : 315,
  "aircraft" : "319"
}, {
  "from" : "MQF",
  "to" : "SVO",
  "airlineDesignator" : "SU",
  "flightNumber" : "1429",
  "departureDate" : [ 2022, 1, 1 ],
  "departureTime" : [ 6, 5 ],
  "arrivalTime" : [ 6, 35 ],
  "travelTimeMinutes" : 150,
  "aircraft" : "32N"
}, {
  "from" : "UFA",
  "to" : "LED",
  "airlineDesignator" : "SU",
  "flightNumber" : "6412",
  "departureDate" : [ 2022, 1, 1 ],
  "departureTime" : [ 6, 5 ],
  "arrivalTime" : [ 6, 50 ],
  "travelTimeMinutes" : 165,
  "aircraft" : "32A"
}, {
  "from" : "SGN",
  "to" : "PQC",
  "airlineDesignator" : "VN",
  "flightNumber" : "6511",
  "departureDate" : [ 2022, 1, 1 ],
  "departureTime" : [ 6, 5 ],
  "arrivalTime" : [ 7, 5 ],
  "travelTimeMinutes" : 60,
  "aircraft" : "320"
}, {
  "from" : "DGO",
  "to" : "MEX",
  "airlineDesignator" : "AM",
  "flightNumber" : "2929",
  "departureDate" : [ 2022, 1, 1 ],
  "departureTime" : [ 6, 9 ],
  "arrivalTime" : [ 7, 50 ],
  "travelTimeMinutes" : 101,
  "aircraft" : "E90"
}, {
  "from" : "RBA",
  "to" : "CDG",
  "airlineDesignator" : "AF",
  "flightNumber" : "1359",
  "departureDate" : [ 2022, 1, 1 ],
  "departureTime" : [ 6, 10 ],
  "arrivalTime" : [ 10, 10 ],
  "travelTimeMinutes" : 180,
  "aircraft" : "321"
}, {
  "from" : "BOD",
  "to" : "AMS",
  "airlineDesignator" : "AF",
  "flightNumber" : "8429*",
  "departureDate" : [ 2022, 1, 1 ],
  "departureTime" : [ 6, 10 ],
  "arrivalTime" : [ 7, 55 ],
  "travelTimeMinutes" : 105,
  "aircraft" : "295"
}, {
  "from" : "PSR",
  "to" : "LIN",
  "airlineDesignator" : "AZ",
  "flightNumber" : "1242*",
  "departureDate" : [ 2022, 1, 1 ],
  "departureTime" : [ 6, 10 ],
  "arrivalTime" : [ 7, 15 ],
  "travelTimeMinutes" : 65,
  "aircraft" : "319"
}, {
  "from" : "ORK",
  "to" : "AMS",
  "airlineDesignator" : "KL",
  "flightNumber" : "1084",
  "departureDate" : [ 2022, 1, 1 ],
  "departureTime" : [ 6, 10 ],
  "arrivalTime" : [ 9, 0 ],
  "travelTimeMinutes" : 110,
  "aircraft" : "E90"
}, {
  "from" : "GOT",
  "to" : "AMS",
  "airlineDesignator" : "KL",
  "flightNumber" : "1152",
  "departureDate" : [ 2022, 1, 1 ],
  "departureTime" : [ 6, 10 ],
  "arrivalTime" : [ 7, 40 ],
  "travelTimeMinutes" : 90,
  "aircraft" : "295"
}, {
  "from" : "KRS",
  "to" : "AMS",
  "airlineDesignator" : "KL",
  "flightNumber" : "1206",
  "departureDate" : [ 2022, 1, 1 ],
  "departureTime" : [ 6, 10 ],
  "arrivalTime" : [ 7, 35 ],
  "travelTimeMinutes" : 85,
  "aircraft" : "E75"
}, {
  "from" : "BOD",
  "to" : "AMS",
  "airlineDesignator" : "KL",
  "flightNumber" : "1312",
  "departureDate" : [ 2022, 1, 1 ],
  "departureTime" : [ 6, 10 ],
  "arrivalTime" : [ 7, 55 ],
  "travelTimeMinutes" : 105,
  "aircraft" : "295"
}, {
  "from" : "BRU",
  "to" : "AMS",
  "airlineDesignator" : "KL",
  "flightNumber" : "1720",
  "departureDate" : [ 2022, 1, 1 ],
  "departureTime" : [ 6, 10 ],
  "arrivalTime" : [ 7, 5 ],
  "travelTimeMinutes" : 55,
  "aircraft" : "E90"
}, {
  "from" : "HAM",
  "to" : "AMS",
  "airlineDesignator" : "KL",
  "flightNumber" : "1776",
  "departureDate" : [ 2022, 1, 1 ],
  "departureTime" : [ 6, 10 ],
  "arrivalTime" : [ 7, 15 ],
  "travelTimeMinutes" : 65,
  "aircraft" : "295"
}, {
  "from" : "PMO",
  "to" : "FCO",
  "airlineDesignator" : "KQ",
  "flightNumber" : "4349*",
  "departureDate" : [ 2022, 1, 1 ],
  "departureTime" : [ 6, 10 ],
  "arrivalTime" : [ 7, 20 ],
  "travelTimeMinutes" : 70,
  "aircraft" : "32S"
}, {
  "from" : "RBA",
  "to" : "CDG",
  "airlineDesignator" : "MU",
  "flightNumber" : "1926*",
  "departureDate" : [ 2022, 1, 1 ],
  "departureTime" : [ 6, 10 ],
  "arrivalTime" : [ 10, 10 ],
  "travelTimeMinutes" : 180,
  "aircraft" : "321"
}, {
  "from" : "WUH",
  "to" : "CAN",
  "airlineDesignator" : "MU",
  "flightNumber" : "6880",
  "departureDate" : [ 2022, 1, 1 ],
  "departureTime" : [ 6, 10 ],
  "arrivalTime" : [ 7, 50 ],
  "travelTimeMinutes" : 100,
  "aircraft" : "73L"
}, {
  "from" : "KJA",
  "to" : "SVO",
  "airlineDesignator" : "SU",
  "flightNumber" : "1481",
  "departureDate" : [ 2022, 1, 1 ],
  "departureTime" : [ 6, 10 ],
  "arrivalTime" : [ 7, 15 ],
  "travelTimeMinutes" : 305,
  "aircraft" : "73H"
}, {
  "from" : "SVO",
  "to" : "AER",
  "airlineDesignator" : "SU",
  "flightNumber" : "1592",
  "departureDate" : [ 2022, 1, 1 ],
  "departureTime" : [ 6, 10 ],
  "arrivalTime" : [ 8, 45 ],
  "travelTimeMinutes" : 155,
  "aircraft" : "32B"
}, {
  "from" : "EVN",
  "to" : "SVO",
  "airlineDesignator" : "SU",
  "flightNumber" : "6610",
  "departureDate" : [ 2022, 1, 1 ],
  "departureTime" : [ 6, 10 ],
  "arrivalTime" : [ 9, 25 ],
  "travelTimeMinutes" : 255,
  "aircraft" : "SU9"
}, {
  "from" : "AHB",
  "to" : "JED",
  "airlineDesignator" : "SV",
  "flightNumber" : "1641",
  "departureDate" : [ 2022, 1, 1 ],
  "departureTime" : [ 6, 10 ],
  "arrivalTime" : [ 7, 20 ],
  "travelTimeMinutes" : 70,
  "aircraft" : "320"
}, {
  "from" : "DXB",
  "to" : "RUH",
  "airlineDesignator" : "SV",
  "flightNumber" : "591",
  "departureDate" : [ 2022, 1, 1 ],
  "departureTime" : [ 6, 10 ],
  "arrivalTime" : [ 7, 10 ],
  "travelTimeMinutes" : 120,
  "aircraft" : "320"
}, {
  "from" : "RUH",
  "to" : "DXB",
  "airlineDesignator" : "SV",
  "flightNumber" : "591",
  "departureDate" : [ 2022, 1, 1 ],
  "departureTime" : [ 6, 10 ],
  "arrivalTime" : [ 7, 10 ],
  "travelTimeMinutes" : 120,
  "aircraft" : "320"
}, {
  "from" : "SGN",
  "to" : "DLI",
  "airlineDesignator" : "VN",
  "flightNumber" : "1380",
  "departureDate" : [ 2022, 1, 1 ],
  "departureTime" : [ 6, 10 ],
  "arrivalTime" : [ 7, 15 ],
  "travelTimeMinutes" : 65,
  "aircraft" : "321"
}, {
  "from" : "SGN",
  "to" : "DAD",
  "airlineDesignator" : "VN",
  "flightNumber" : "6052",
  "departureDate" : [ 2022, 1, 1 ],
  "departureTime" : [ 6, 10 ],
  "arrivalTime" : [ 7, 30 ],
  "travelTimeMinutes" : 80,
  "aircraft" : "320"
}, {
  "from" : "BCN",
  "to" : "CDG",
  "airlineDesignator" : "AF",
  "flightNumber" : "1449",
  "departureDate" : [ 2022, 1, 1 ],
  "departureTime" : [ 6, 15 ],
  "arrivalTime" : [ 8, 10 ],
  "travelTimeMinutes" : 115,
  "aircraft" : "321"
}, {
  "from" : "ORY",
  "to" : "MRS",
  "airlineDesignator" : "AF",
  "flightNumber" : "6002",
  "departureDate" : [ 2022, 1, 1 ],
  "departureTime" : [ 6, 15 ],
  "arrivalTime" : [ 7, 30 ],
  "travelTimeMinutes" : 75,
  "aircraft" : "318"
}, {
  "from" : "LYS",
  "to" : "AMS",
  "airlineDesignator" : "AF",
  "flightNumber" : "8320*",
  "departureDate" : [ 2022, 1, 1 ],
  "departureTime" : [ 6, 15 ],
  "arrivalTime" : [ 7, 50 ],
  "travelTimeMinutes" : 95,
  "aircraft" : "295"
}, {
  "from" : "BRI",
  "to" : "LIN",
  "airlineDesignator" : "AZ",
  "flightNumber" : "1646*",
  "departureDate" : [ 2022, 1, 1 ],
  "departureTime" : [ 6, 15 ],
  "arrivalTime" : [ 7, 40 ],
  "travelTimeMinutes" : 85,
  "aircraft" : "CRK"
}, {
  "from" : "SUB",
  "to" : "CGK",
  "airlineDesignator" : "CI",
  "flightNumber" : "9775*",
  "departureDate" : [ 2022, 1, 1 ],
  "departureTime" : [ 6, 15 ],
  "arrivalTime" : [ 7, 50 ],
  "travelTimeMinutes" : 95,
  "aircraft" : "738"
}, {
  "from" : "YHZ",
  "to" : "YYZ",
  "airlineDesignator" : "DL",
  "flightNumber" : "7019*",
  "departureDate" : [ 2022, 1, 1 ],
  "departureTime" : [ 6, 15 ],
  "arrivalTime" : [ 7, 39 ],
  "travelTimeMinutes" : 144,
  "aircraft" : "7M8"
}, {
  "from" : "YYJ",
  "to" : "YVR",
  "airlineDesignator" : "DL",
  "flightNumber" : "7244*",
  "departureDate" : [ 2022, 1, 1 ],
  "departureTime" : [ 6, 15 ],
  "arrivalTime" : [ 6, 50 ],
  "travelTimeMinutes" : 35,
  "aircraft" : "DH4"
}, {
  "from" : "SUB",
  "to" : "CGK",
  "airlineDesignator" : "GA",
  "flightNumber" : "305",
  "departureDate" : [ 2022, 1, 1 ],
  "departureTime" : [ 6, 15 ],
  "arrivalTime" : [ 7, 50 ],
  "travelTimeMinutes" : 95,
  "aircraft" : "738"
}, {
  "from" : "YYJ",
  "to" : "YVR",
  "airlineDesignator" : "KE",
  "flightNumber" : "6503*",
  "departureDate" : [ 2022, 1, 1 ],
  "departureTime" : [ 6, 15 ],
  "arrivalTime" : [ 6, 50 ],
  "travelTimeMinutes" : 35,
  "aircraft" : "DH4"
}, {
  "from" : "YHZ",
  "to" : "YYZ",
  "airlineDesignator" : "KE",
  "flightNumber" : "6552*",
  "departureDate" : [ 2022, 1, 1 ],
  "departureTime" : [ 6, 15 ],
  "arrivalTime" : [ 7, 39 ],
  "travelTimeMinutes" : 144,
  "aircraft" : "7M8"
}, {
  "from" : "LYS",
  "to" : "AMS",
  "airlineDesignator" : "KL",
  "flightNumber" : "1412",
  "departureDate" : [ 2022, 1, 1 ],
  "departureTime" : [ 6, 15 ],
  "arrivalTime" : [ 7, 50 ],
  "travelTimeMinutes" : 95,
  "aircraft" : "295"
}, {
  "from" : "LUX",
  "to" : "AMS",
  "airlineDesignator" : "KL",
  "flightNumber" : "1736",
  "departureDate" : [ 2022, 1, 1 ],
  "departureTime" : [ 6, 15 ],
  "arrivalTime" : [ 7, 20 ],
  "travelTimeMinutes" : 65,
  "aircraft" : "E75"
}, {
  "from" : "ZAG",
  "to" : "AMS",
  "airlineDesignator" : "KL",
  "flightNumber" : "1938",
  "departureDate" : [ 2022, 1, 1 ],
  "departureTime" : [ 6, 15 ],
  "arrivalTime" : [ 8, 15 ],
  "travelTimeMinutes" : 120,
  "aircraft" : "73W"
}, {
  "from" : "XIY",
  "to" : "DSN",
  "airlineDesignator" : "MU",
  "flightNumber" : "2323",
  "departureDate" : [ 2022, 1, 1 ],
  "departureTime" : [ 6, 15 ],
  "arrivalTime" : [ 7, 45 ],
  "travelTimeMinutes" : 90,
  "aircraft" : "320"
}, {
  "from" : "PVG",
  "to" : "HDG",
  "airlineDesignator" : "MU",
  "flightNumber" : "5637",
  "departureDate" : [ 2022, 1, 1 ],
  "departureTime" : [ 6, 15 ],
  "arrivalTime" : [ 8, 35 ],
  "travelTimeMinutes" : 140,
  "aircraft" : "320"
}, {
  "from" : "HGH",
  "to" : "XIY",
  "airlineDesignator" : "MU",
  "flightNumber" : "9042",
  "departureDate" : [ 2022, 1, 1 ],
  "departureTime" : [ 6, 15 ],
  "arrivalTime" : [ 8, 35 ],
  "travelTimeMinutes" : 140,
  "aircraft" : "320"
}, {
  "from" : "SVO",
  "to" : "OMS",
  "airlineDesignator" : "SU",
  "flightNumber" : "1640",
  "departureDate" : [ 2022, 1, 1 ],
  "departureTime" : [ 6, 15 ],
  "arrivalTime" : [ 12, 35 ],
  "travelTimeMinutes" : 200,
  "aircraft" : "73H"
}, {
  "from" : "CEK",
  "to" : "LED",
  "airlineDesignator" : "SU",
  "flightNumber" : "6462",
  "departureDate" : [ 2022, 1, 1 ],
  "departureTime" : [ 6, 15 ],
  "arrivalTime" : [ 7, 15 ],
  "travelTimeMinutes" : 180,
  "aircraft" : "319"
}, {
  "from" : "VOZ",
  "to" : "SVO",
  "airlineDesignator" : "SU",
  "flightNumber" : "6468",
  "departureDate" : [ 2022, 1, 1 ],
  "departureTime" : [ 6, 15 ],
  "arrivalTime" : [ 7, 30 ],
  "travelTimeMinutes" : 75,
  "aircraft" : "SU9"
}, {
  "from" : "JED",
  "to" : "AHB",
  "airlineDesignator" : "SV",
  "flightNumber" : "1642",
  "departureDate" : [ 2022, 1, 1 ],
  "departureTime" : [ 6, 15 ],
  "arrivalTime" : [ 7, 30 ],
  "travelTimeMinutes" : 75,
  "aircraft" : "320"
}, {
  "from" : "AHB",
  "to" : "RUH",
  "airlineDesignator" : "SV",
  "flightNumber" : "1662",
  "departureDate" : [ 2022, 1, 1 ],
  "departureTime" : [ 6, 15 ],
  "arrivalTime" : [ 7, 50 ],
  "travelTimeMinutes" : 95,
  "aircraft" : "330"
}, {
  "from" : "SUB",
  "to" : "CGK",
  "airlineDesignator" : "SV",
  "flightNumber" : "6157*",
  "departureDate" : [ 2022, 1, 1 ],
  "departureTime" : [ 6, 15 ],
  "arrivalTime" : [ 7, 50 ],
  "travelTimeMinutes" : 95,
  "aircraft" : "738"
}, {
  "from" : "BCN",
  "to" : "CDG",
  "airlineDesignator" : "UX",
  "flightNumber" : "2208*",
  "departureDate" : [ 2022, 1, 1 ],
  "departureTime" : [ 6, 15 ],
  "arrivalTime" : [ 8, 10 ],
  "travelTimeMinutes" : 115,
  "aircraft" : "321"
}, {
  "from" : "SGN",
  "to" : "PQC",
  "airlineDesignator" : "VN",
  "flightNumber" : "1823",
  "departureDate" : [ 2022, 1, 1 ],
  "departureTime" : [ 6, 15 ],
  "arrivalTime" : [ 7, 20 ],
  "travelTimeMinutes" : 65,
  "aircraft" : "321"
}, {
  "from" : "LHR",
  "to" : "CDG",
  "airlineDesignator" : "AF",
  "flightNumber" : "1381",
  "departureDate" : [ 2022, 1, 1 ],
  "departureTime" : [ 6, 20 ],
  "arrivalTime" : [ 8, 35 ],
  "travelTimeMinutes" : 75,
  "aircraft" : "320"
}, {
  "from" : "HAJ",
  "to" : "CDG",
  "airlineDesignator" : "AF",
  "flightNumber" : "1439*",
  "departureDate" : [ 2022, 1, 1 ],
  "departureTime" : [ 6, 20 ],
  "arrivalTime" : [ 7, 55 ],
  "travelTimeMinutes" : 95,
  "aircraft" : "E70"
}, {
  "from" : "CDG",
  "to" : "MRS",
  "airlineDesignator" : "AF",
  "flightNumber" : "7673",
  "departureDate" : [ 2022, 1, 1 ],
  "departureTime" : [ 6, 20 ],
  "arrivalTime" : [ 7, 50 ],
  "travelTimeMinutes" : 90,
  "aircraft" : "321"
}, {
  "from" : "MRS",
  "to" : "CDG",
  "airlineDesignator" : "AF",
  "flightNumber" : "7673",
  "departureDate" : [ 2022, 1, 1 ],
  "departureTime" : [ 6, 20 ],
  "arrivalTime" : [ 7, 50 ],
  "travelTimeMinutes" : 90,
  "aircraft" : "321"
}, {
  "from" : "BCN",
  "to" : "AMS",
  "airlineDesignator" : "CI",
  "flightNumber" : "9394*",
  "departureDate" : [ 2022, 1, 1 ],
  "departureTime" : [ 6, 20 ],
  "arrivalTime" : [ 8, 40 ],
  "travelTimeMinutes" : 140,
  "aircraft" : "73H"
}, {
  "from" : "BOS",
  "to" : "EWR",
  "airlineDesignator" : "DL",
  "flightNumber" : "5681",
  "departureDate" : [ 2022, 1, 1 ],
  "departureTime" : [ 6, 20 ],
  "arrivalTime" : [ 7, 45 ],
  "travelTimeMinutes" : 85,
  "aircraft" : "E75"
}, {
  "from" : "SIN",
  "to" : "CGK",
  "airlineDesignator" : "GA",
  "flightNumber" : "8950*",
  "departureDate" : [ 2022, 1, 1 ],
  "departureTime" : [ 6, 20 ],
  "arrivalTime" : [ 7, 5 ],
  "travelTimeMinutes" : 105,
  "aircraft" : "77W"
}, {
  "from" : "SVG",
  "to" : "AMS",
  "airlineDesignator" : "KL",
  "flightNumber" : "1196",
  "departureDate" : [ 2022, 1, 1 ],
  "departureTime" : [ 6, 20 ],
  "arrivalTime" : [ 7, 55 ],
  "travelTimeMinutes" : 95,
  "aircraft" : "E90"
}, {
  "from" : "TRN",
  "to" : "AMS",
  "airlineDesignator" : "KL",
  "flightNumber" : "1554",
  "departureDate" : [ 2022, 1, 1 ],
  "departureTime" : [ 6, 20 ],
  "arrivalTime" : [ 8, 20 ],
  "travelTimeMinutes" : 120,
  "aircraft" : "E75"
}, {
  "from" : "BCN",
  "to" : "AMS",
  "airlineDesignator" : "KL",
  "flightNumber" : "1662",
  "departureDate" : [ 2022, 1, 1 ],
  "departureTime" : [ 6, 20 ],
  "arrivalTime" : [ 8, 40 ],
  "travelTimeMinutes" : 140,
  "aircraft" : "73H"
}, {
  "from" : "BRE",
  "to" : "AMS",
  "airlineDesignator" : "KL",
  "flightNumber" : "1750",
  "departureDate" : [ 2022, 1, 1 ],
  "departureTime" : [ 6, 20 ],
  "arrivalTime" : [ 7, 15 ],
  "travelTimeMinutes" : 55,
  "aircraft" : "E75"
}, {
  "from" : "DUS",
  "to" : "AMS",
  "airlineDesignator" : "KL",
  "flightNumber" : "1852",
  "departureDate" : [ 2022, 1, 1 ],
  "departureTime" : [ 6, 20 ],
  "arrivalTime" : [ 7, 15 ],
  "travelTimeMinutes" : 55,
  "aircraft" : "E90"
}, {
  "from" : "HAJ",
  "to" : "CDG",
  "airlineDesignator" : "KQ",
  "flightNumber" : "3761*",
  "departureDate" : [ 2022, 1, 1 ],
  "departureTime" : [ 6, 20 ],
  "arrivalTime" : [ 7, 55 ],
  "travelTimeMinutes" : 95,
  "aircraft" : "E70"
}, {
  "from" : "CKG",
  "to" : "SHA",
  "airlineDesignator" : "MU",
  "flightNumber" : "5422",
  "departureDate" : [ 2022, 1, 1 ],
  "departureTime" : [ 6, 20 ],
  "arrivalTime" : [ 8, 40 ],
  "travelTimeMinutes" : 140,
  "aircraft" : "320"
}, {
  "from" : "PVG",
  "to" : "BPE",
  "airlineDesignator" : "MU",
  "flightNumber" : "8371*",
  "departureDate" : [ 2022, 1, 1 ],
  "departureTime" : [ 6, 20 ],
  "arrivalTime" : [ 8, 35 ],
  "travelTimeMinutes" : 135,
  "aircraft" : "73H"
}, {
  "from" : "SGN",
  "to" : "BMV",
  "airlineDesignator" : "VN",
  "flightNumber" : "1414",
  "departureDate" : [ 2022, 1, 1 ],
  "departureTime" : [ 6, 20 ],
  "arrivalTime" : [ 7, 25 ],
  "travelTimeMinutes" : 65,
  "aircraft" : "321"
}, {
  "from" : "SLP",
  "to" : "MEX",
  "airlineDesignator" : "AM",
  "flightNumber" : "2539",
  "departureDate" : [ 2022, 1, 1 ],
  "departureTime" : [ 6, 23 ],
  "arrivalTime" : [ 7, 30 ],
  "travelTimeMinutes" : 67,
  "aircraft" : "E90"
}, {
  "from" : "VER",
  "to" : "MEX",
  "airlineDesignator" : "AM",
  "flightNumber" : "851",
  "departureDate" : [ 2022, 1, 1 ],
  "departureTime" : [ 6, 23 ],
  "arrivalTime" : [ 7, 30 ],
  "travelTimeMinutes" : 67,
  "aircraft" : "E90"
}, {
  "from" : "CDG",
  "to" : "OSL",
  "airlineDesignator" : "AF",
  "flightNumber" : "1275",
  "departureDate" : [ 2022, 1, 1 ],
  "departureTime" : [ 6, 25 ],
  "arrivalTime" : [ 8, 55 ],
  "travelTimeMinutes" : 150,
  "aircraft" : "319"
}, {
  "from" : "OSL",
  "to" : "CDG",
  "airlineDesignator" : "AF",
  "flightNumber" : "1275",
  "departureDate" : [ 2022, 1, 1 ],
  "departureTime" : [ 6, 25 ],
  "arrivalTime" : [ 8, 55 ],
  "travelTimeMinutes" : 150,
  "aircraft" : "319"
}, {
  "from" : "CPH",
  "to" : "CDG",
  "airlineDesignator" : "AF",
  "flightNumber" : "1351",
  "departureDate" : [ 2022, 1, 1 ],
  "departureTime" : [ 6, 25 ],
  "arrivalTime" : [ 8, 25 ],
  "travelTimeMinutes" : 120,
  "aircraft" : "223"
}, {
  "from" : "MEX",
  "to" : "DGO",
  "airlineDesignator" : "AM",
  "flightNumber" : "2428",
  "departureDate" : [ 2022, 1, 1 ],
  "departureTime" : [ 6, 25 ],
  "arrivalTime" : [ 8, 7 ],
  "travelTimeMinutes" : 102,
  "aircraft" : "E90"
}, {
  "from" : "CDG",
  "to" : "OSL",
  "airlineDesignator" : "AM",
  "flightNumber" : "6070*",
  "departureDate" : [ 2022, 1, 1 ],
  "departureTime" : [ 6, 25 ],
  "arrivalTime" : [ 8, 55 ],
  "travelTimeMinutes" : 150,
  "aircraft" : "319"
}, {
  "from" : "OSL",
  "to" : "CDG",
  "airlineDesignator" : "AM",
  "flightNumber" : "6070*",
  "departureDate" : [ 2022, 1, 1 ],
  "departureTime" : [ 6, 25 ],
  "arrivalTime" : [ 8, 55 ],
  "travelTimeMinutes" : 150,
  "aircraft" : "319"
}, {
  "from" : "SUF",
  "to" : "FCO",
  "airlineDesignator" : "AZ",
  "flightNumber" : "1162*",
  "departureDate" : [ 2022, 1, 1 ],
  "departureTime" : [ 6, 25 ],
  "arrivalTime" : [ 7, 35 ],
  "travelTimeMinutes" : 70,
  "aircraft" : "320"
}, {
  "from" : "GDN",
  "to" : "AMS",
  "airlineDesignator" : "KL",
  "flightNumber" : "1916",
  "departureDate" : [ 2022, 1, 1 ],
  "departureTime" : [ 6, 25 ],
  "arrivalTime" : [ 8, 15 ],
  "travelTimeMinutes" : 110,
  "aircraft" : "E90"
}, {
  "from" : "SUF",
  "to" : "FCO",
  "airlineDesignator" : "KQ",
  "flightNumber" : "4355*",
  "departureDate" : [ 2022, 1, 1 ],
  "departureTime" : [ 6, 25 ],
  "arrivalTime" : [ 7, 35 ],
  "travelTimeMinutes" : 70,
  "aircraft" : "32S"
}, {
  "from" : "CAN",
  "to" : "CGQ",
  "airlineDesignator" : "MU",
  "flightNumber" : "6895",
  "departureDate" : [ 2022, 1, 1 ],
  "departureTime" : [ 6, 25 ],
  "arrivalTime" : [ 12, 25 ],
  "travelTimeMinutes" : 360,
  "aircraft" : "73E"
}, {
  "from" : "SVO",
  "to" : "OVB",
  "airlineDesignator" : "SU",
  "flightNumber" : "1462",
  "departureDate" : [ 2022, 1, 1 ],
  "departureTime" : [ 6, 25 ],
  "arrivalTime" : [ 14, 25 ],
  "travelTimeMinutes" : 240,
  "aircraft" : "73H"
}, {
  "from" : "SVO",
  "to" : "KUF",
  "airlineDesignator" : "SU",
  "flightNumber" : "1602",
  "departureDate" : [ 2022, 1, 1 ],
  "departureTime" : [ 6, 25 ],
  "arrivalTime" : [ 9, 10 ],
  "travelTimeMinutes" : 105,
  "aircraft" : "73H"
}, {
  "from" : "IST",
  "to" : "SVO",
  "airlineDesignator" : "SU",
  "flightNumber" : "2139",
  "departureDate" : [ 2022, 1, 1 ],
  "departureTime" : [ 6, 25 ],
  "arrivalTime" : [ 11, 55 ],
  "travelTimeMinutes" : 330,
  "aircraft" : "333"
}, {
  "from" : "REN",
  "to" : "LED",
  "airlineDesignator" : "SU",
  "flightNumber" : "6454",
  "departureDate" : [ 2022, 1, 1 ],
  "departureTime" : [ 6, 25 ],
  "arrivalTime" : [ 7, 20 ],
  "travelTimeMinutes" : 175,
  "aircraft" : "319"
}, {
  "from" : "RUH",
  "to" : "KRT",
  "airlineDesignator" : "SV",
  "flightNumber" : "459",
  "departureDate" : [ 2022, 1, 1 ],
  "departureTime" : [ 6, 25 ],
  "arrivalTime" : [ 8, 10 ],
  "travelTimeMinutes" : 165,
  "aircraft" : "330"
}, {
  "from" : "RUH",
  "to" : "DXB",
  "airlineDesignator" : "SV",
  "flightNumber" : "562",
  "departureDate" : [ 2022, 1, 1 ],
  "departureTime" : [ 6, 25 ],
  "arrivalTime" : [ 9, 25 ],
  "travelTimeMinutes" : 120,
  "aircraft" : "320"
}, {
  "from" : "CDG",
  "to" : "OSL",
  "airlineDesignator" : "SV",
  "flightNumber" : "6275*",
  "departureDate" : [ 2022, 1, 1 ],
  "departureTime" : [ 6, 25 ],
  "arrivalTime" : [ 8, 55 ],
  "travelTimeMinutes" : 150,
  "aircraft" : "319"
}, {
  "from" : "OSL",
  "to" : "CDG",
  "airlineDesignator" : "SV",
  "flightNumber" : "6275*",
  "departureDate" : [ 2022, 1, 1 ],
  "departureTime" : [ 6, 25 ],
  "arrivalTime" : [ 8, 55 ],
  "travelTimeMinutes" : 150,
  "aircraft" : "319"
}, {
  "from" : "SUF",
  "to" : "FCO",
  "airlineDesignator" : "SV",
  "flightNumber" : "6734*",
  "departureDate" : [ 2022, 1, 1 ],
  "departureTime" : [ 6, 25 ],
  "arrivalTime" : [ 7, 35 ],
  "travelTimeMinutes" : 70,
  "aircraft" : "32S"
}, {
  "from" : "HEL",
  "to" : "CDG",
  "airlineDesignator" : "AF",
  "flightNumber" : "1177",
  "departureDate" : [ 2022, 1, 1 ],
  "departureTime" : [ 6, 30 ],
  "arrivalTime" : [ 8, 35 ],
  "travelTimeMinutes" : 185,
  "aircraft" : "223"
}, {
  "from" : "ORY",
  "to" : "NCE",
  "airlineDesignator" : "AF",
  "flightNumber" : "6200",
  "departureDate" : [ 2022, 1, 1 ],
  "departureTime" : [ 6, 30 ],
  "arrivalTime" : [ 7, 55 ],
  "travelTimeMinutes" : 85,
  "aircraft" : "318"
}, {
  "from" : "NCE",
  "to" : "AMS",
  "airlineDesignator" : "AF",
  "flightNumber" : "8270*",
  "departureDate" : [ 2022, 1, 1 ],
  "departureTime" : [ 6, 30 ],
  "arrivalTime" : [ 8, 30 ],
  "travelTimeMinutes" : 120,
  "aircraft" : "295"
}, {
  "from" : "MEX",
  "to" : "VSA",
  "airlineDesignator" : "AM",
  "flightNumber" : "800",
  "departureDate" : [ 2022, 1, 1 ],
  "departureTime" : [ 6, 30 ],
  "arrivalTime" : [ 8, 2 ],
  "travelTimeMinutes" : 92,
  "aircraft" : "7M7"
}, {
  "from" : "TUC",
  "to" : "AEP",
  "airlineDesignator" : "AR",
  "flightNumber" : "1489",
  "departureDate" : [ 2022, 1, 1 ],
  "departureTime" : [ 6, 30 ],
  "arrivalTime" : [ 8, 15 ],
  "travelTimeMinutes" : 105,
  "aircraft" : "E90"
}, {
  "from" : "NAP",
  "to" : "FCO",
  "airlineDesignator" : "AZ",
  "flightNumber" : "1268*",
  "departureDate" : [ 2022, 1, 1 ],
  "departureTime" : [ 6, 30 ],
  "arrivalTime" : [ 7, 20 ],
  "travelTimeMinutes" : 50,
  "aircraft" : "319"
}, {
  "from" : "BLQ",
  "to" : "FCO",
  "airlineDesignator" : "AZ",
  "flightNumber" : "1312*",
  "departureDate" : [ 2022, 1, 1 ],
  "departureTime" : [ 6, 30 ],
  "arrivalTime" : [ 7, 30 ],
  "travelTimeMinutes" : 60,
  "aircraft" : "319"
}, {
  "from" : "LHR",
  "to" : "AMS",
  "airlineDesignator" : "CI",
  "flightNumber" : "9362*",
  "departureDate" : [ 2022, 1, 1 ],
  "departureTime" : [ 6, 30 ],
  "arrivalTime" : [ 8, 55 ],
  "travelTimeMinutes" : 85,
  "aircraft" : "73H"
}, {
  "from" : "CGK",
  "to" : "PNK",
  "airlineDesignator" : "CI",
  "flightNumber" : "9682*",
  "departureDate" : [ 2022, 1, 1 ],
  "departureTime" : [ 6, 30 ],
  "arrivalTime" : [ 8, 10 ],
  "travelTimeMinutes" : 100,
  "aircraft" : "738"
}, {
  "from" : "MCI",
  "to" : "DTW",
  "airlineDesignator" : "DL",
  "flightNumber" : "1367",
  "departureDate" : [ 2022, 1, 1 ],
  "departureTime" : [ 6, 30 ],
  "arrivalTime" : [ 9, 25 ],
  "travelTimeMinutes" : 115,
  "aircraft" : "717"
}, {
  "from" : "YYZ",
  "to" : "YEG",
  "airlineDesignator" : "DL",
  "flightNumber" : "6887*",
  "departureDate" : [ 2022, 1, 1 ],
  "departureTime" : [ 6, 30 ],
  "arrivalTime" : [ 12, 5 ],
  "travelTimeMinutes" : 215,
  "aircraft" : "73H"
}, {
  "from" : "YXU",
  "to" : "YYZ",
  "airlineDesignator" : "DL",
  "flightNumber" : "6964*",
  "departureDate" : [ 2022, 1, 1 ],
  "departureTime" : [ 6, 30 ],
  "arrivalTime" : [ 7, 19 ],
  "travelTimeMinutes" : 49,
  "aircraft" : "DH4"
}, {
  "from" : "YQR",
  "to" : "YYC",
  "airlineDesignator" : "DL",
  "flightNumber" : "7078*",
  "departureDate" : [ 2022, 1, 1 ],
  "departureTime" : [ 6, 30 ],
  "arrivalTime" : [ 8, 23 ],
  "travelTimeMinutes" : 113,
  "aircraft" : "DH4"
}, {
  "from" : "CGK",
  "to" : "PNK",
  "airlineDesignator" : "GA",
  "flightNumber" : "502",
  "departureDate" : [ 2022, 1, 1 ],
  "departureTime" : [ 6, 30 ],
  "arrivalTime" : [ 8, 10 ],
  "travelTimeMinutes" : 100,
  "aircraft" : "738"
}, {
  "from" : "LHR",
  "to" : "AMS",
  "airlineDesignator" : "KL",
  "flightNumber" : "1000",
  "departureDate" : [ 2022, 1, 1 ],
  "departureTime" : [ 6, 30 ],
  "arrivalTime" : [ 8, 55 ],
  "travelTimeMinutes" : 85,
  "aircraft" : "73H"
}, {
  "from" : "ARN",
  "to" : "AMS",
  "airlineDesignator" : "KL",
  "flightNumber" : "1104",
  "departureDate" : [ 2022, 1, 1 ],
  "departureTime" : [ 6, 30 ],
  "arrivalTime" : [ 8, 40 ],
  "travelTimeMinutes" : 130,
  "aircraft" : "73H"
}, {
  "from" : "OSL",
  "to" : "AMS",
  "airlineDesignator" : "KL",
  "flightNumber" : "1140",
  "departureDate" : [ 2022, 1, 1 ],
  "departureTime" : [ 6, 30 ],
  "arrivalTime" : [ 8, 15 ],
  "travelTimeMinutes" : 105,
  "aircraft" : "E90"
}, {
  "from" : "NCE",
  "to" : "AMS",
  "airlineDesignator" : "KL",
  "flightNumber" : "1250",
  "departureDate" : [ 2022, 1, 1 ],
  "departureTime" : [ 6, 30 ],
  "arrivalTime" : [ 8, 30 ],
  "travelTimeMinutes" : 120,
  "aircraft" : "295"
}, {
  "from" : "FCO",
  "to" : "AMS",
  "airlineDesignator" : "KL",
  "flightNumber" : "1596",
  "departureDate" : [ 2022, 1, 1 ],
  "departureTime" : [ 6, 30 ],
  "arrivalTime" : [ 8, 50 ],
  "travelTimeMinutes" : 140,
  "aircraft" : "73H"
}, {
  "from" : "PUF",
  "to" : "CDG",
  "airlineDesignator" : "KQ",
  "flightNumber" : "3125*",
  "departureDate" : [ 2022, 1, 1 ],
  "departureTime" : [ 6, 30 ],
  "arrivalTime" : [ 8, 0 ],
  "travelTimeMinutes" : 90,
  "aircraft" : "E90"
}, {
  "from" : "NBO",
  "to" : "MBA",
  "airlineDesignator" : "KQ",
  "flightNumber" : "600",
  "departureDate" : [ 2022, 1, 1 ],
  "departureTime" : [ 6, 30 ],
  "arrivalTime" : [ 7, 30 ],
  "travelTimeMinutes" : 60,
  "aircraft" : "E90"
}, {
  "from" : "NCE",
  "to" : "AMS",
  "airlineDesignator" : "MF",
  "flightNumber" : "9838*",
  "departureDate" : [ 2022, 1, 1 ],
  "departureTime" : [ 6, 30 ],
  "arrivalTime" : [ 8, 30 ],
  "travelTimeMinutes" : 120,
  "aircraft" : "295"
}, {
  "from" : "XIY",
  "to" : "SHE",
  "airlineDesignator" : "MU",
  "flightNumber" : "2183",
  "departureDate" : [ 2022, 1, 1 ],
  "departureTime" : [ 6, 30 ],
  "arrivalTime" : [ 9, 20 ],
  "travelTimeMinutes" : 170,
  "aircraft" : "320"
}, {
  "from" : "XIY",
  "to" : "SHA",
  "airlineDesignator" : "MU",
  "flightNumber" : "2239",
  "departureDate" : [ 2022, 1, 1 ],
  "departureTime" : [ 6, 30 ],
  "arrivalTime" : [ 8, 50 ],
  "travelTimeMinutes" : 140,
  "aircraft" : "333"
}, {
  "from" : "SHA",
  "to" : "SWA",
  "airlineDesignator" : "MU",
  "flightNumber" : "5263",
  "departureDate" : [ 2022, 1, 1 ],
  "departureTime" : [ 6, 30 ],
  "arrivalTime" : [ 8, 40 ],
  "travelTimeMinutes" : 130,
  "aircraft" : "EQV"
}, {
  "from" : "CAN",
  "to" : "KMG",
  "airlineDesignator" : "MU",
  "flightNumber" : "6823",
  "departureDate" : [ 2022, 1, 1 ],
  "departureTime" : [ 6, 30 ],
  "arrivalTime" : [ 8, 55 ],
  "travelTimeMinutes" : 145,
  "aircraft" : "73L"
}, {
  "from" : "KWL",
  "to" : "PVG",
  "airlineDesignator" : "MU",
  "flightNumber" : "8324*",
  "departureDate" : [ 2022, 1, 1 ],
  "departureTime" : [ 6, 30 ],
  "arrivalTime" : [ 8, 55 ],
  "travelTimeMinutes" : 145,
  "aircraft" : "738"
}, {
  "from" : "PVG",
  "to" : "XNN",
  "airlineDesignator" : "MU",
  "flightNumber" : "8470*",
  "departureDate" : [ 2022, 1, 1 ],
  "departureTime" : [ 6, 30 ],
  "arrivalTime" : [ 9, 55 ],
  "travelTimeMinutes" : 205,
  "aircraft" : "73E"
}, {
  "from" : "RMF",
  "to" : "PRG",
  "airlineDesignator" : "OK",
  "flightNumber" : "4275*",
  "departureDate" : [ 2022, 1, 1 ],
  "departureTime" : [ 6, 30 ],
  "arrivalTime" : [ 11, 10 ],
  "travelTimeMinutes" : 280,
  "aircraft" : "738"
}, {
  "from" : "SVO",
  "to" : "AAQ",
  "airlineDesignator" : "SU",
  "flightNumber" : "1146",
  "departureDate" : [ 2022, 1, 1 ],
  "departureTime" : [ 6, 30 ],
  "arrivalTime" : [ 8, 50 ],
  "travelTimeMinutes" : 140,
  "aircraft" : "32A"
}, {
  "from" : "SVO",
  "to" : "REN",
  "airlineDesignator" : "SU",
  "flightNumber" : "1246",
  "departureDate" : [ 2022, 1, 1 ],
  "departureTime" : [ 6, 30 ],
  "arrivalTime" : [ 10, 40 ],
  "travelTimeMinutes" : 130,
  "aircraft" : "32A"
}, {
  "from" : "SVO",
  "to" : "SGC",
  "airlineDesignator" : "SU",
  "flightNumber" : "1516",
  "departureDate" : [ 2022, 1, 1 ],
  "departureTime" : [ 6, 30 ],
  "arrivalTime" : [ 11, 45 ],
  "travelTimeMinutes" : 195,
  "aircraft" : "32N"
}, {
  "from" : "SVO",
  "to" : "SIP",
  "airlineDesignator" : "SU",
  "flightNumber" : "1582",
  "departureDate" : [ 2022, 1, 1 ],
  "departureTime" : [ 6, 30 ],
  "arrivalTime" : [ 9, 10 ],
  "travelTimeMinutes" : 160,
  "aircraft" : "32Q"
}, {
  "from" : "LED",
  "to" : "KGD",
  "airlineDesignator" : "SU",
  "flightNumber" : "6321",
  "departureDate" : [ 2022, 1, 1 ],
  "departureTime" : [ 6, 30 ],
  "arrivalTime" : [ 7, 40 ],
  "travelTimeMinutes" : 130,
  "aircraft" : "320"
}, {
  "from" : "GIZ",
  "to" : "JED",
  "airlineDesignator" : "SV",
  "flightNumber" : "1763",
  "departureDate" : [ 2022, 1, 1 ],
  "departureTime" : [ 6, 30 ],
  "arrivalTime" : [ 7, 50 ],
  "travelTimeMinutes" : 80,
  "aircraft" : "320"
}, {
  "from" : "MAD",
  "to" : "LIS",
  "airlineDesignator" : "SV",
  "flightNumber" : "6131*",
  "departureDate" : [ 2022, 1, 1 ],
  "departureTime" : [ 6, 30 ],
  "arrivalTime" : [ 6, 50 ],
  "travelTimeMinutes" : 80,
  "aircraft" : "73H"
}, {
  "from" : "MAD",
  "to" : "LIS",
  "airlineDesignator" : "UX",
  "flightNumber" : "1159",
  "departureDate" : [ 2022, 1, 1 ],
  "departureTime" : [ 6, 30 ],
  "arrivalTime" : [ 6, 50 ],
  "travelTimeMinutes" : 80,
  "aircraft" : "73H"
}, {
  "from" : "CUL",
  "to" : "MEX",
  "airlineDesignator" : "AM",
  "flightNumber" : "1161",
  "departureDate" : [ 2022, 1, 1 ],
  "departureTime" : [ 6, 34 ],
  "arrivalTime" : [ 9, 35 ],
  "travelTimeMinutes" : 121,
  "aircraft" : "E90"
}, {
  "from" : "FLR",
  "to" : "FCO",
  "airlineDesignator" : "AZ",
  "flightNumber" : "1676*",
  "departureDate" : [ 2022, 1, 1 ],
  "departureTime" : [ 6, 35 ],
  "arrivalTime" : [ 7, 25 ],
  "travelTimeMinutes" : 50,
  "aircraft" : "319"
}, {
  "from" : "PEN",
  "to" : "KUL",
  "airlineDesignator" : "CI",
  "flightNumber" : "9427*",
  "departureDate" : [ 2022, 1, 1 ],
  "departureTime" : [ 6, 35 ],
  "arrivalTime" : [ 7, 40 ],
  "travelTimeMinutes" : 65,
  "aircraft" : "738"
}, {
  "from" : "PEN",
  "to" : "KUL",
  "airlineDesignator" : "GA",
  "flightNumber" : "8882*",
  "departureDate" : [ 2022, 1, 1 ],
  "departureTime" : [ 6, 35 ],
  "arrivalTime" : [ 7, 40 ],
  "travelTimeMinutes" : 65,
  "aircraft" : "738"
}, {
  "from" : "CGK",
  "to" : "NRT",
  "airlineDesignator" : "GA",
  "flightNumber" : "9150*",
  "departureDate" : [ 2022, 1, 1 ],
  "departureTime" : [ 6, 35 ],
  "arrivalTime" : [ 16, 5 ],
  "travelTimeMinutes" : 450,
  "aircraft" : "788"
}, {
  "from" : "SZX",
  "to" : "CGQ",
  "airlineDesignator" : "MF",
  "flightNumber" : "8043",
  "departureDate" : [ 2022, 1, 1 ],
  "departureTime" : [ 6, 35 ],
  "arrivalTime" : [ 12, 20 ],
  "travelTimeMinutes" : 345,
  "aircraft" : "738"
}, {
  "from" : "XMN",
  "to" : "CGQ",
  "airlineDesignator" : "MF",
  "flightNumber" : "8075",
  "departureDate" : [ 2022, 1, 1 ],
  "departureTime" : [ 6, 35 ],
  "arrivalTime" : [ 11, 50 ],
  "travelTimeMinutes" : 315,
  "aircraft" : "738"
}, {
  "from" : "XMN",
  "to" : "HSN",
  "airlineDesignator" : "MF",
  "flightNumber" : "8575",
  "departureDate" : [ 2022, 1, 1 ],
  "departureTime" : [ 6, 35 ],
  "arrivalTime" : [ 8, 10 ],
  "travelTimeMinutes" : 95,
  "aircraft" : "738"
}, {
  "from" : "PVG",
  "to" : "NBS",
  "airlineDesignator" : "MU",
  "flightNumber" : "3479*",
  "departureDate" : [ 2022, 1, 1 ],
  "departureTime" : [ 6, 35 ],
  "arrivalTime" : [ 12, 0 ],
  "travelTimeMinutes" : 325,
  "aircraft" : "32A"
}, {
  "from" : "SHA",
  "to" : "YNT",
  "airlineDesignator" : "MU",
  "flightNumber" : "8345*",
  "departureDate" : [ 2022, 1, 1 ],
  "departureTime" : [ 6, 35 ],
  "arrivalTime" : [ 8, 35 ],
  "travelTimeMinutes" : 120,
  "aircraft" : "738"
}, {
  "from" : "PVG",
  "to" : "LUM",
  "airlineDesignator" : "MU",
  "flightNumber" : "9760",
  "departureDate" : [ 2022, 1, 1 ],
  "departureTime" : [ 6, 35 ],
  "arrivalTime" : [ 10, 50 ],
  "travelTimeMinutes" : 255,
  "aircraft" : "737"
}, {
  "from" : "KUF",
  "to" : "SVO",
  "airlineDesignator" : "SU",
  "flightNumber" : "1217",
  "departureDate" : [ 2022, 1, 1 ],
  "departureTime" : [ 6, 35 ],
  "arrivalTime" : [ 7, 25 ],
  "travelTimeMinutes" : 110,
  "aircraft" : "32A"
}, {
  "from" : "DUS",
  "to" : "CDG",
  "airlineDesignator" : "AF",
  "flightNumber" : "1107*",
  "departureDate" : [ 2022, 1, 1 ],
  "departureTime" : [ 6, 40 ],
  "arrivalTime" : [ 7, 55 ],
  "travelTimeMinutes" : 75,
  "aircraft" : "E90"
}, {
  "from" : "SXB",
  "to" : "AMS",
  "airlineDesignator" : "AF",
  "flightNumber" : "4054*",
  "departureDate" : [ 2022, 1, 1 ],
  "departureTime" : [ 6, 40 ],
  "arrivalTime" : [ 8, 5 ],
  "travelTimeMinutes" : 85,
  "aircraft" : "ER4"
}, {
  "from" : "MEX",
  "to" : "OAX",
  "airlineDesignator" : "AM",
  "flightNumber" : "2046",
  "departureDate" : [ 2022, 1, 1 ],
  "departureTime" : [ 6, 40 ],
  "arrivalTime" : [ 7, 48 ],
  "travelTimeMinutes" : 68,
  "aircraft" : "E90"
}, {
  "from" : "MEX",
  "to" : "TAM",
  "airlineDesignator" : "AM",
  "flightNumber" : "2410",
  "departureDate" : [ 2022, 1, 1 ],
  "departureTime" : [ 6, 40 ],
  "arrivalTime" : [ 7, 44 ],
  "travelTimeMinutes" : 64,
  "aircraft" : "E90"
}, {
  "from" : "MEX",
  "to" : "LAX",
  "airlineDesignator" : "AM",
  "flightNumber" : "646",
  "departureDate" : [ 2022, 1, 1 ],
  "departureTime" : [ 6, 40 ],
  "arrivalTime" : [ 9, 7 ],
  "travelTimeMinutes" : 267,
  "aircraft" : "7M8"
}, {
  "from" : "MEX",
  "to" : "CME",
  "airlineDesignator" : "AM",
  "flightNumber" : "814",
  "departureDate" : [ 2022, 1, 1 ],
  "departureTime" : [ 6, 40 ],
  "arrivalTime" : [ 8, 16 ],
  "travelTimeMinutes" : 96,
  "aircraft" : "7S8"
}, {
  "from" : "GMP",
  "to" : "CJU",
  "airlineDesignator" : "KE",
  "flightNumber" : "1201",
  "departureDate" : [ 2022, 1, 1 ],
  "departureTime" : [ 6, 40 ],
  "arrivalTime" : [ 7, 50 ],
  "travelTimeMinutes" : 70,
  "aircraft" : "739"
}, {
  "from" : "LIN",
  "to" : "AMS",
  "airlineDesignator" : "KL",
  "flightNumber" : "1618",
  "departureDate" : [ 2022, 1, 1 ],
  "departureTime" : [ 6, 40 ],
  "arrivalTime" : [ 8, 40 ],
  "travelTimeMinutes" : 120,
  "aircraft" : "E90"
}, {
  "from" : "MXP",
  "to" : "AMS",
  "airlineDesignator" : "KL",
  "flightNumber" : "1628",
  "departureDate" : [ 2022, 1, 1 ],
  "departureTime" : [ 6, 40 ],
  "arrivalTime" : [ 8, 35 ],
  "travelTimeMinutes" : 115,
  "aircraft" : "73H"
}, {
  "from" : "DUS",
  "to" : "CDG",
  "airlineDesignator" : "KQ",
  "flightNumber" : "3053*",
  "departureDate" : [ 2022, 1, 1 ],
  "departureTime" : [ 6, 40 ],
  "arrivalTime" : [ 7, 55 ],
  "travelTimeMinutes" : 75,
  "aircraft" : "E90"
}, {
  "from" : "XMN",
  "to" : "TSN",
  "airlineDesignator" : "MF",
  "flightNumber" : "8275",
  "departureDate" : [ 2022, 1, 1 ],
  "departureTime" : [ 6, 40 ],
  "arrivalTime" : [ 9, 40 ],
  "travelTimeMinutes" : 180,
  "aircraft" : "738"
}, {
  "from" : "XIY",
  "to" : "WUH",
  "airlineDesignator" : "MU",
  "flightNumber" : "2125",
  "departureDate" : [ 2022, 1, 1 ],
  "departureTime" : [ 6, 40 ],
  "arrivalTime" : [ 8, 15 ],
  "travelTimeMinutes" : 95,
  "aircraft" : "320"
}, {
  "from" : "DSN",
  "to" : "XIY",
  "airlineDesignator" : "MU",
  "flightNumber" : "2426",
  "departureDate" : [ 2022, 1, 1 ],
  "departureTime" : [ 6, 40 ],
  "arrivalTime" : [ 7, 55 ],
  "travelTimeMinutes" : 75,
  "aircraft" : "320"
}, {
  "from" : "CKG",
  "to" : "PVG",
  "airlineDesignator" : "MU",
  "flightNumber" : "5502",
  "departureDate" : [ 2022, 1, 1 ],
  "departureTime" : [ 6, 40 ],
  "arrivalTime" : [ 8, 55 ],
  "travelTimeMinutes" : 135,
  "aircraft" : "320"
}, {
  "from" : "CAN",
  "to" : "WNZ",
  "airlineDesignator" : "MU",
  "flightNumber" : "6321",
  "departureDate" : [ 2022, 1, 1 ],
  "departureTime" : [ 6, 40 ],
  "arrivalTime" : [ 8, 35 ],
  "travelTimeMinutes" : 115,
  "aircraft" : "73L"
}, {
  "from" : "HRB",
  "to" : "DSN",
  "airlineDesignator" : "MU",
  "flightNumber" : "6463",
  "departureDate" : [ 2022, 1, 1 ],
  "departureTime" : [ 6, 40 ],
  "arrivalTime" : [ 9, 35 ],
  "travelTimeMinutes" : 175,
  "aircraft" : "320"
}, {
  "from" : "XIY",
  "to" : "YIW",
  "airlineDesignator" : "MU",
  "flightNumber" : "6509",
  "departureDate" : [ 2022, 1, 1 ],
  "departureTime" : [ 6, 40 ],
  "arrivalTime" : [ 9, 5 ],
  "travelTimeMinutes" : 145,
  "aircraft" : "319"
}, {
  "from" : "SYX",
  "to" : "CGQ",
  "airlineDesignator" : "MU",
  "flightNumber" : "6543",
  "departureDate" : [ 2022, 1, 1 ],
  "departureTime" : [ 6, 40 ],
  "arrivalTime" : [ 13, 30 ],
  "travelTimeMinutes" : 410,
  "aircraft" : "320"
}, {
  "from" : "CAN",
  "to" : "JGN",
  "airlineDesignator" : "MU",
  "flightNumber" : "6955",
  "departureDate" : [ 2022, 1, 1 ],
  "departureTime" : [ 6, 40 ],
  "arrivalTime" : [ 12, 30 ],
  "travelTimeMinutes" : 350,
  "aircraft" : "73L"
}, {
  "from" : "PVG",
  "to" : "KHN",
  "airlineDesignator" : "MU",
  "flightNumber" : "9065",
  "departureDate" : [ 2022, 1, 1 ],
  "departureTime" : [ 6, 40 ],
  "arrivalTime" : [ 8, 35 ],
  "travelTimeMinutes" : 115,
  "aircraft" : "EQV"
}, {
  "from" : "SVO",
  "to" : "KGD",
  "airlineDesignator" : "SU",
  "flightNumber" : "1000",
  "departureDate" : [ 2022, 1, 1 ],
  "departureTime" : [ 6, 40 ],
  "arrivalTime" : [ 8, 20 ],
  "travelTimeMinutes" : 160,
  "aircraft" : "32A"
}, {
  "from" : "HBE",
  "to" : "JED",
  "airlineDesignator" : "SV",
  "flightNumber" : "332",
  "departureDate" : [ 2022, 1, 1 ],
  "departureTime" : [ 6, 40 ],
  "arrivalTime" : [ 10, 5 ],
  "travelTimeMinutes" : 145,
  "aircraft" : "321"
}, {
  "from" : "MAD",
  "to" : "BIO",
  "airlineDesignator" : "UX",
  "flightNumber" : "7161",
  "departureDate" : [ 2022, 1, 1 ],
  "departureTime" : [ 6, 40 ],
  "arrivalTime" : [ 7, 40 ],
  "travelTimeMinutes" : 60,
  "aircraft" : "73H"
}, {
  "from" : "MAD",
  "to" : "LCG",
  "airlineDesignator" : "UX",
  "flightNumber" : "7233",
  "departureDate" : [ 2022, 1, 1 ],
  "departureTime" : [ 6, 40 ],
  "arrivalTime" : [ 7, 50 ],
  "travelTimeMinutes" : 70,
  "aircraft" : "73H"
}, {
  "from" : "SGN",
  "to" : "VCL",
  "airlineDesignator" : "VN",
  "flightNumber" : "1460",
  "departureDate" : [ 2022, 1, 1 ],
  "departureTime" : [ 6, 40 ],
  "arrivalTime" : [ 8, 5 ],
  "travelTimeMinutes" : 85,
  "aircraft" : "321"
}, {
  "from" : "MNL",
  "to" : "SGN",
  "airlineDesignator" : "VN",
  "flightNumber" : "3941*",
  "departureDate" : [ 2022, 1, 1 ],
  "departureTime" : [ 6, 40 ],
  "arrivalTime" : [ 8, 30 ],
  "travelTimeMinutes" : 170,
  "aircraft" : "321"
}, {
  "from" : "SGN",
  "to" : "VII",
  "airlineDesignator" : "VN",
  "flightNumber" : "6430",
  "departureDate" : [ 2022, 1, 1 ],
  "departureTime" : [ 6, 40 ],
  "arrivalTime" : [ 8, 30 ],
  "travelTimeMinutes" : 110,
  "aircraft" : "320"
}, {
  "from" : "OAX",
  "to" : "MEX",
  "airlineDesignator" : "AM",
  "flightNumber" : "2407",
  "departureDate" : [ 2022, 1, 1 ],
  "departureTime" : [ 6, 42 ],
  "arrivalTime" : [ 8, 0 ],
  "travelTimeMinutes" : 78,
  "aircraft" : "E90"
}, {
  "from" : "LJU",
  "to" : "CDG",
  "airlineDesignator" : "AF",
  "flightNumber" : "1187*",
  "departureDate" : [ 2022, 1, 1 ],
  "departureTime" : [ 6, 45 ],
  "arrivalTime" : [ 8, 45 ],
  "travelTimeMinutes" : 120,
  "aircraft" : "E90"
}, {
  "from" : "CAG",
  "to" : "LIN",
  "airlineDesignator" : "AZ",
  "flightNumber" : "1561*",
  "departureDate" : [ 2022, 1, 1 ],
  "departureTime" : [ 6, 45 ],
  "arrivalTime" : [ 8, 5 ],
  "travelTimeMinutes" : 80,
  "aircraft" : "32S"
}, {
  "from" : "LHR",
  "to" : "LIN",
  "airlineDesignator" : "AZ",
  "flightNumber" : "229*",
  "departureDate" : [ 2022, 1, 1 ],
  "departureTime" : [ 6, 45 ],
  "arrivalTime" : [ 9, 40 ],
  "travelTimeMinutes" : 115,
  "aircraft" : "319"
}, {
  "from" : "YOW",
  "to" : "YYZ",
  "airlineDesignator" : "DL",
  "flightNumber" : "6896*",
  "departureDate" : [ 2022, 1, 1 ],
  "departureTime" : [ 6, 45 ],
  "arrivalTime" : [ 7, 47 ],
  "travelTimeMinutes" : 62,
  "aircraft" : "7M8"
}, {
  "from" : "YYZ",
  "to" : "YOW",
  "airlineDesignator" : "DL",
  "flightNumber" : "6896*",
  "departureDate" : [ 2022, 1, 1 ],
  "departureTime" : [ 6, 45 ],
  "arrivalTime" : [ 7, 47 ],
  "travelTimeMinutes" : 62,
  "aircraft" : "7M8"
}, {
  "from" : "AMS",
  "to" : "BRU",
  "airlineDesignator" : "KL",
  "flightNumber" : "1721",
  "departureDate" : [ 2022, 1, 1 ],
  "departureTime" : [ 6, 45 ],
  "arrivalTime" : [ 7, 30 ],
  "travelTimeMinutes" : 45,
  "aircraft" : "E90"
}, {
  "from" : "MUC",
  "to" : "AMS",
  "airlineDesignator" : "KL",
  "flightNumber" : "1790",
  "departureDate" : [ 2022, 1, 1 ],
  "departureTime" : [ 6, 45 ],
  "arrivalTime" : [ 8, 20 ],
  "travelTimeMinutes" : 95,
  "aircraft" : "73H"
}, {
  "from" : "LJU",
  "to" : "CDG",
  "airlineDesignator" : "KQ",
  "flightNumber" : "3787*",
  "departureDate" : [ 2022, 1, 1 ],
  "departureTime" : [ 6, 45 ],
  "arrivalTime" : [ 8, 45 ],
  "travelTimeMinutes" : 120,
  "aircraft" : "E90"
}, {
  "from" : "XMN",
  "to" : "LYG",
  "airlineDesignator" : "MF",
  "flightNumber" : "8051",
  "departureDate" : [ 2022, 1, 1 ],
  "departureTime" : [ 6, 45 ],
  "arrivalTime" : [ 9, 20 ],
  "travelTimeMinutes" : 155,
  "aircraft" : "738"
}, {
  "from" : "XMN",
  "to" : "CKG",
  "airlineDesignator" : "MF",
  "flightNumber" : "8403",
  "departureDate" : [ 2022, 1, 1 ],
  "departureTime" : [ 6, 45 ],
  "arrivalTime" : [ 9, 25 ],
  "travelTimeMinutes" : 160,
  "aircraft" : "738"
}, {
  "from" : "PVG",
  "to" : "LXA",
  "airlineDesignator" : "MU",
  "flightNumber" : "2335",
  "departureDate" : [ 2022, 1, 1 ],
  "departureTime" : [ 6, 45 ],
  "arrivalTime" : [ 14, 15 ],
  "travelTimeMinutes" : 450,
  "aircraft" : "319"
}, {
  "from" : "SHA",
  "to" : "HET",
  "airlineDesignator" : "MU",
  "flightNumber" : "5459",
  "departureDate" : [ 2022, 1, 1 ],
  "departureTime" : [ 6, 45 ],
  "arrivalTime" : [ 9, 30 ],
  "travelTimeMinutes" : 165,
  "aircraft" : "73L"
}, {
  "from" : "KMG",
  "to" : "SYM",
  "airlineDesignator" : "MU",
  "flightNumber" : "5917",
  "departureDate" : [ 2022, 1, 1 ],
  "departureTime" : [ 6, 45 ],
  "arrivalTime" : [ 7, 45 ],
  "travelTimeMinutes" : 60,
  "aircraft" : "737"
}, {
  "from" : "PVG",
  "to" : "KWL",
  "airlineDesignator" : "MU",
  "flightNumber" : "6403",
  "departureDate" : [ 2022, 1, 1 ],
  "departureTime" : [ 6, 45 ],
  "arrivalTime" : [ 9, 30 ],
  "travelTimeMinutes" : 165,
  "aircraft" : "321"
}, {
  "from" : "CSX",
  "to" : "NKG",
  "airlineDesignator" : "MU",
  "flightNumber" : "6550",
  "departureDate" : [ 2022, 1, 1 ],
  "departureTime" : [ 6, 45 ],
  "arrivalTime" : [ 8, 15 ],
  "travelTimeMinutes" : 90,
  "aircraft" : "320"
}, {
  "from" : "PVG",
  "to" : "SHE",
  "airlineDesignator" : "MU",
  "flightNumber" : "8393*",
  "departureDate" : [ 2022, 1, 1 ],
  "departureTime" : [ 6, 45 ],
  "arrivalTime" : [ 9, 10 ],
  "travelTimeMinutes" : 145,
  "aircraft" : "73H"
}, {
  "from" : "SHA",
  "to" : "KWE",
  "airlineDesignator" : "MU",
  "flightNumber" : "8609*",
  "departureDate" : [ 2022, 1, 1 ],
  "departureTime" : [ 6, 45 ],
  "arrivalTime" : [ 9, 30 ],
  "travelTimeMinutes" : 165,
  "aircraft" : "73E"
}, {
  "from" : "SVO",
  "to" : "SVX",
  "airlineDesignator" : "SU",
  "flightNumber" : "1410",
  "departureDate" : [ 2022, 1, 1 ],
  "departureTime" : [ 6, 45 ],
  "arrivalTime" : [ 11, 10 ],
  "travelTimeMinutes" : 145,
  "aircraft" : "32B"
}, {
  "from" : "VKO",
  "to" : "LED",
  "airlineDesignator" : "SU",
  "flightNumber" : "6022",
  "departureDate" : [ 2022, 1, 1 ],
  "departureTime" : [ 6, 45 ],
  "arrivalTime" : [ 8, 5 ],
  "travelTimeMinutes" : 80,
  "aircraft" : "SU9"
}, {
  "from" : "OVB",
  "to" : "LED",
  "airlineDesignator" : "SU",
  "flightNumber" : "6542",
  "departureDate" : [ 2022, 1, 1 ],
  "departureTime" : [ 6, 45 ],
  "arrivalTime" : [ 7, 20 ],
  "travelTimeMinutes" : 275,
  "aircraft" : "32A"
}, {
  "from" : "MAD",
  "to" : "OPO",
  "airlineDesignator" : "UX",
  "flightNumber" : "1147",
  "departureDate" : [ 2022, 1, 1 ],
  "departureTime" : [ 6, 45 ],
  "arrivalTime" : [ 7, 0 ],
  "travelTimeMinutes" : 75,
  "aircraft" : "E90"
}, {
  "from" : "MAD",
  "to" : "AGP",
  "airlineDesignator" : "UX",
  "flightNumber" : "5035",
  "departureDate" : [ 2022, 1, 1 ],
  "departureTime" : [ 6, 45 ],
  "arrivalTime" : [ 8, 0 ],
  "travelTimeMinutes" : 75,
  "aircraft" : "E90"
}, {
  "from" : "VCS",
  "to" : "SGN",
  "airlineDesignator" : "VN",
  "flightNumber" : "1890",
  "departureDate" : [ 2022, 1, 1 ],
  "departureTime" : [ 6, 45 ],
  "arrivalTime" : [ 7, 50 ],
  "travelTimeMinutes" : 65,
  "aircraft" : "AT7"
}, {
  "from" : "KCH",
  "to" : "KUL",
  "airlineDesignator" : "CI",
  "flightNumber" : "9417*",
  "departureDate" : [ 2022, 1, 1 ],
  "departureTime" : [ 6, 50 ],
  "arrivalTime" : [ 8, 40 ],
  "travelTimeMinutes" : 110,
  "aircraft" : "738"
}, {
  "from" : "KCH",
  "to" : "KUL",
  "airlineDesignator" : "GA",
  "flightNumber" : "9292*",
  "departureDate" : [ 2022, 1, 1 ],
  "departureTime" : [ 6, 50 ],
  "arrivalTime" : [ 8, 40 ],
  "travelTimeMinutes" : 110,
  "aircraft" : "738"
}, {
  "from" : "AMS",
  "to" : "ARN",
  "airlineDesignator" : "KL",
  "flightNumber" : "1105",
  "departureDate" : [ 2022, 1, 1 ],
  "departureTime" : [ 6, 50 ],
  "arrivalTime" : [ 8, 50 ],
  "travelTimeMinutes" : 120,
  "aircraft" : "73H"
}, {
  "from" : "AMS",
  "to" : "VIE",
  "airlineDesignator" : "KL",
  "flightNumber" : "1839",
  "departureDate" : [ 2022, 1, 1 ],
  "departureTime" : [ 6, 50 ],
  "arrivalTime" : [ 8, 35 ],
  "travelTimeMinutes" : 105,
  "aircraft" : "73H"
}, {
  "from" : "AMS",
  "to" : "DUS",
  "airlineDesignator" : "KL",
  "flightNumber" : "1853",
  "departureDate" : [ 2022, 1, 1 ],
  "departureTime" : [ 6, 50 ],
  "arrivalTime" : [ 7, 40 ],
  "travelTimeMinutes" : 50,
  "aircraft" : "E90"
}, {
  "from" : "JRO",
  "to" : "NBO",
  "airlineDesignator" : "KQ",
  "flightNumber" : "6717*",
  "departureDate" : [ 2022, 1, 1 ],
  "departureTime" : [ 6, 50 ],
  "arrivalTime" : [ 7, 50 ],
  "travelTimeMinutes" : 60,
  "aircraft" : "AT7"
}, {
  "from" : "HGH",
  "to" : "TYN",
  "airlineDesignator" : "MF",
  "flightNumber" : "8179",
  "departureDate" : [ 2022, 1, 1 ],
  "departureTime" : [ 6, 50 ],
  "arrivalTime" : [ 9, 5 ],
  "travelTimeMinutes" : 135,
  "aircraft" : "738"
}, {
  "from" : "TSN",
  "to" : "LHW",
  "airlineDesignator" : "MF",
  "flightNumber" : "8227",
  "departureDate" : [ 2022, 1, 1 ],
  "departureTime" : [ 6, 50 ],
  "arrivalTime" : [ 9, 20 ],
  "travelTimeMinutes" : 150,
  "aircraft" : "738"
}, {
  "from" : "HGH",
  "to" : "CSX",
  "airlineDesignator" : "MF",
  "flightNumber" : "8229",
  "departureDate" : [ 2022, 1, 1 ],
  "departureTime" : [ 6, 50 ],
  "arrivalTime" : [ 8, 35 ],
  "travelTimeMinutes" : 105,
  "aircraft" : "738"
}, {
  "from" : "XMN",
  "to" : "CGO",
  "airlineDesignator" : "MF",
  "flightNumber" : "8373",
  "departureDate" : [ 2022, 1, 1 ],
  "departureTime" : [ 6, 50 ],
  "arrivalTime" : [ 9, 15 ],
  "travelTimeMinutes" : 145,
  "aircraft" : "738"
}, {
  "from" : "HGH",
  "to" : "NAO",
  "airlineDesignator" : "MF",
  "flightNumber" : "8485",
  "departureDate" : [ 2022, 1, 1 ],
  "departureTime" : [ 6, 50 ],
  "arrivalTime" : [ 11, 25 ],
  "travelTimeMinutes" : 275,
  "aircraft" : "738"
}, {
  "from" : "JJN",
  "to" : "HSN",
  "airlineDesignator" : "MF",
  "flightNumber" : "8539",
  "departureDate" : [ 2022, 1, 1 ],
  "departureTime" : [ 6, 50 ],
  "arrivalTime" : [ 8, 20 ],
  "travelTimeMinutes" : 90,
  "aircraft" : "738"
}, {
  "from" : "TYN",
  "to" : "KMG",
  "airlineDesignator" : "MU",
  "flightNumber" : "2143",
  "departureDate" : [ 2022, 1, 1 ],
  "departureTime" : [ 6, 50 ],
  "arrivalTime" : [ 9, 25 ],
  "travelTimeMinutes" : 155,
  "aircraft" : "73H"
}, {
  "from" : "UYN",
  "to" : "SHA",
  "airlineDesignator" : "MU",
  "flightNumber" : "2155",
  "departureDate" : [ 2022, 1, 1 ],
  "departureTime" : [ 6, 50 ],
  "arrivalTime" : [ 13, 10 ],
  "travelTimeMinutes" : 380,
  "aircraft" : "321"
}, {
  "from" : "NKG",
  "to" : "CSX",
  "airlineDesignator" : "MU",
  "flightNumber" : "2753",
  "departureDate" : [ 2022, 1, 1 ],
  "departureTime" : [ 6, 50 ],
  "arrivalTime" : [ 8, 30 ],
  "travelTimeMinutes" : 100,
  "aircraft" : "320"
}, {
  "from" : "CKG",
  "to" : "KMG",
  "airlineDesignator" : "MU",
  "flightNumber" : "5449",
  "departureDate" : [ 2022, 1, 1 ],
  "departureTime" : [ 6, 50 ],
  "arrivalTime" : [ 8, 25 ],
  "travelTimeMinutes" : 95,
  "aircraft" : "320"
}, {
  "from" : "KHN",
  "to" : "DSN",
  "airlineDesignator" : "MU",
  "flightNumber" : "5551",
  "departureDate" : [ 2022, 1, 1 ],
  "departureTime" : [ 6, 50 ],
  "arrivalTime" : [ 11, 15 ],
  "travelTimeMinutes" : 265,
  "aircraft" : "320"
}, {
  "from" : "HRB",
  "to" : "NGB",
  "airlineDesignator" : "MU",
  "flightNumber" : "5649",
  "departureDate" : [ 2022, 1, 1 ],
  "departureTime" : [ 6, 50 ],
  "arrivalTime" : [ 9, 55 ],
  "travelTimeMinutes" : 185,
  "aircraft" : "320"
}, {
  "from" : "KMG",
  "to" : "LUM",
  "airlineDesignator" : "MU",
  "flightNumber" : "5971",
  "departureDate" : [ 2022, 1, 1 ],
  "departureTime" : [ 6, 50 ],
  "arrivalTime" : [ 7, 55 ],
  "travelTimeMinutes" : 65,
  "aircraft" : "737"
}, {
  "from" : "CAN",
  "to" : "DAT",
  "airlineDesignator" : "MU",
  "flightNumber" : "6733",
  "departureDate" : [ 2022, 1, 1 ],
  "departureTime" : [ 6, 50 ],
  "arrivalTime" : [ 11, 55 ],
  "travelTimeMinutes" : 305,
  "aircraft" : "73E"
}, {
  "from" : "SHA",
  "to" : "JXA",
  "airlineDesignator" : "MU",
  "flightNumber" : "8445*",
  "departureDate" : [ 2022, 1, 1 ],
  "departureTime" : [ 6, 50 ],
  "arrivalTime" : [ 11, 45 ],
  "travelTimeMinutes" : 295,
  "aircraft" : "733"
}, {
  "from" : "SHA",
  "to" : "SYX",
  "airlineDesignator" : "MU",
  "flightNumber" : "8643*",
  "departureDate" : [ 2022, 1, 1 ],
  "departureTime" : [ 6, 50 ],
  "arrivalTime" : [ 10, 0 ],
  "travelTimeMinutes" : 190,
  "aircraft" : "321"
}, {
  "from" : "LED",
  "to" : "KZN",
  "airlineDesignator" : "SU",
  "flightNumber" : "6593",
  "departureDate" : [ 2022, 1, 1 ],
  "departureTime" : [ 6, 50 ],
  "arrivalTime" : [ 9, 5 ],
  "travelTimeMinutes" : 135,
  "aircraft" : "SU9"
}, {
  "from" : "MAD",
  "to" : "VGO",
  "airlineDesignator" : "UX",
  "flightNumber" : "7308",
  "departureDate" : [ 2022, 1, 1 ],
  "departureTime" : [ 6, 50 ],
  "arrivalTime" : [ 7, 55 ],
  "travelTimeMinutes" : 65,
  "aircraft" : "73H"
}, {
  "from" : "HAN",
  "to" : "VCL",
  "airlineDesignator" : "VN",
  "flightNumber" : "1641",
  "departureDate" : [ 2022, 1, 1 ],
  "departureTime" : [ 6, 50 ],
  "arrivalTime" : [ 8, 20 ],
  "travelTimeMinutes" : 90,
  "aircraft" : "321"
}, {
  "from" : "PNH",
  "to" : "SGN",
  "airlineDesignator" : "VN",
  "flightNumber" : "3852*",
  "departureDate" : [ 2022, 1, 1 ],
  "departureTime" : [ 6, 50 ],
  "arrivalTime" : [ 7, 50 ],
  "travelTimeMinutes" : 60,
  "aircraft" : "AT7"
}, {
  "from" : "MRS",
  "to" : "AMS",
  "airlineDesignator" : "AF",
  "flightNumber" : "1806*",
  "departureDate" : [ 2022, 1, 1 ],
  "departureTime" : [ 6, 55 ],
  "arrivalTime" : [ 8, 55 ],
  "travelTimeMinutes" : 120,
  "aircraft" : "E90"
}, {
  "from" : "AJA",
  "to" : "ORY",
  "airlineDesignator" : "AF",
  "flightNumber" : "4442*",
  "departureDate" : [ 2022, 1, 1 ],
  "departureTime" : [ 6, 55 ],
  "arrivalTime" : [ 8, 35 ],
  "travelTimeMinutes" : 100,
  "aircraft" : "320"
}, {
  "from" : "BIA",
  "to" : "ORY",
  "airlineDesignator" : "AF",
  "flightNumber" : "4458*",
  "departureDate" : [ 2022, 1, 1 ],
  "departureTime" : [ 6, 55 ],
  "arrivalTime" : [ 8, 35 ],
  "travelTimeMinutes" : 100,
  "aircraft" : "320"
}, {
  "from" : "YWG",
  "to" : "MSP",
  "airlineDesignator" : "DL",
  "flightNumber" : "1283",
  "departureDate" : [ 2022, 1, 1 ],
  "departureTime" : [ 6, 55 ],
  "arrivalTime" : [ 8, 20 ],
  "travelTimeMinutes" : 85,
  "aircraft" : "320"
}, {
  "from" : "MRS",
  "to" : "AMS",
  "airlineDesignator" : "KL",
  "flightNumber" : "3597*",
  "departureDate" : [ 2022, 1, 1 ],
  "departureTime" : [ 6, 55 ],
  "arrivalTime" : [ 8, 55 ],
  "travelTimeMinutes" : 120,
  "aircraft" : "E90"
}, {
  "from" : "IST",
  "to" : "BEY",
  "airlineDesignator" : "ME",
  "flightNumber" : "2830*",
  "departureDate" : [ 2022, 1, 1 ],
  "departureTime" : [ 6, 55 ],
  "arrivalTime" : [ 8, 45 ],
  "travelTimeMinutes" : 110,
  "aircraft" : "333"
}, {
  "from" : "HRB",
  "to" : "CSX",
  "airlineDesignator" : "MF",
  "flightNumber" : "8040",
  "departureDate" : [ 2022, 1, 1 ],
  "departureTime" : [ 6, 55 ],
  "arrivalTime" : [ 12, 50 ],
  "travelTimeMinutes" : 355,
  "aircraft" : "738"
}, {
  "from" : "XMN",
  "to" : "XIY",
  "airlineDesignator" : "MF",
  "flightNumber" : "8217",
  "departureDate" : [ 2022, 1, 1 ],
  "departureTime" : [ 6, 55 ],
  "arrivalTime" : [ 9, 50 ],
  "travelTimeMinutes" : 175,
  "aircraft" : "738"
}, {
  "from" : "XMN",
  "to" : "WUH",
  "airlineDesignator" : "MF",
  "flightNumber" : "8337",
  "departureDate" : [ 2022, 1, 1 ],
  "departureTime" : [ 6, 55 ],
  "arrivalTime" : [ 8, 50 ],
  "travelTimeMinutes" : 115,
  "aircraft" : "738"
}, {
  "from" : "HGH",
  "to" : "SZX",
  "airlineDesignator" : "MF",
  "flightNumber" : "8383",
  "departureDate" : [ 2022, 1, 1 ],
  "departureTime" : [ 6, 55 ],
  "arrivalTime" : [ 9, 15 ],
  "travelTimeMinutes" : 140,
  "aircraft" : "738"
}, {
  "from" : "TSN",
  "to" : "XMN",
  "airlineDesignator" : "MF",
  "flightNumber" : "8980",
  "departureDate" : [ 2022, 1, 1 ],
  "departureTime" : [ 6, 55 ],
  "arrivalTime" : [ 9, 55 ],
  "travelTimeMinutes" : 180,
  "aircraft" : "738"
}, {
  "from" : "XIY",
  "to" : "LXA",
  "airlineDesignator" : "MU",
  "flightNumber" : "2439",
  "departureDate" : [ 2022, 1, 1 ],
  "departureTime" : [ 6, 55 ],
  "arrivalTime" : [ 10, 10 ],
  "travelTimeMinutes" : 195,
  "aircraft" : "319"
}, {
  "from" : "TYN",
  "to" : "SHA",
  "airlineDesignator" : "MU",
  "flightNumber" : "5273",
  "departureDate" : [ 2022, 1, 1 ],
  "departureTime" : [ 6, 55 ],
  "arrivalTime" : [ 8, 55 ],
  "travelTimeMinutes" : 120,
  "aircraft" : "73L"
}, {
  "from" : "CTU",
  "to" : "PVG",
  "airlineDesignator" : "MU",
  "flightNumber" : "5402",
  "departureDate" : [ 2022, 1, 1 ],
  "departureTime" : [ 6, 55 ],
  "arrivalTime" : [ 9, 55 ],
  "travelTimeMinutes" : 180,
  "aircraft" : "320"
}, {
  "from" : "SHA",
  "to" : "TNA",
  "airlineDesignator" : "MU",
  "flightNumber" : "5571",
  "departureDate" : [ 2022, 1, 1 ],
  "departureTime" : [ 6, 55 ],
  "arrivalTime" : [ 8, 50 ],
  "travelTimeMinutes" : 115,
  "aircraft" : "73L"
}, {
  "from" : "HGH",
  "to" : "TAO",
  "airlineDesignator" : "MU",
  "flightNumber" : "5671",
  "departureDate" : [ 2022, 1, 1 ],
  "departureTime" : [ 6, 55 ],
  "arrivalTime" : [ 8, 45 ],
  "travelTimeMinutes" : 110,
  "aircraft" : "320"
}, {
  "from" : "KMG",
  "to" : "BSD",
  "airlineDesignator" : "MU",
  "flightNumber" : "5983",
  "departureDate" : [ 2022, 1, 1 ],
  "departureTime" : [ 6, 55 ],
  "arrivalTime" : [ 7, 55 ],
  "travelTimeMinutes" : 60,
  "aircraft" : "737"
}, {
  "from" : "SHE",
  "to" : "PVG",
  "airlineDesignator" : "MU",
  "flightNumber" : "6313",
  "departureDate" : [ 2022, 1, 1 ],
  "departureTime" : [ 6, 55 ],
  "arrivalTime" : [ 9, 55 ],
  "travelTimeMinutes" : 180,
  "aircraft" : "320"
}, {
  "from" : "KMG",
  "to" : "HGH",
  "airlineDesignator" : "MU",
  "flightNumber" : "6482",
  "departureDate" : [ 2022, 1, 1 ],
  "departureTime" : [ 6, 55 ],
  "arrivalTime" : [ 9, 45 ],
  "travelTimeMinutes" : 170,
  "aircraft" : "320"
}, {
  "from" : "SHA",
  "to" : "FOC",
  "airlineDesignator" : "MU",
  "flightNumber" : "8423*",
  "departureDate" : [ 2022, 1, 1 ],
  "departureTime" : [ 6, 55 ],
  "arrivalTime" : [ 8, 20 ],
  "travelTimeMinutes" : 85,
  "aircraft" : "73L"
}, {
  "from" : "KZN",
  "to" : "SVO",
  "airlineDesignator" : "SU",
  "flightNumber" : "1199",
  "departureDate" : [ 2022, 1, 1 ],
  "departureTime" : [ 6, 55 ],
  "arrivalTime" : [ 8, 35 ],
  "travelTimeMinutes" : 100,
  "aircraft" : "73H"
}, {
  "from" : "UFA",
  "to" : "SVO",
  "airlineDesignator" : "SU",
  "flightNumber" : "1261",
  "departureDate" : [ 2022, 1, 1 ],
  "departureTime" : [ 6, 55 ],
  "arrivalTime" : [ 7, 20 ],
  "travelTimeMinutes" : 145,
  "aircraft" : "32A"
}, {
  "from" : "HMA",
  "to" : "SVO",
  "airlineDesignator" : "SU",
  "flightNumber" : "1383",
  "departureDate" : [ 2022, 1, 1 ],
  "departureTime" : [ 6, 55 ],
  "arrivalTime" : [ 8, 10 ],
  "travelTimeMinutes" : 195,
  "aircraft" : "32A"
}, {
  "from" : "SVO",
  "to" : "SIP",
  "airlineDesignator" : "SU",
  "flightNumber" : "1650",
  "departureDate" : [ 2022, 1, 1 ],
  "departureTime" : [ 6, 55 ],
  "arrivalTime" : [ 9, 40 ],
  "travelTimeMinutes" : 165,
  "aircraft" : "73H"
}, {
  "from" : "LED",
  "to" : "SVX",
  "airlineDesignator" : "SU",
  "flightNumber" : "6419",
  "departureDate" : [ 2022, 1, 1 ],
  "departureTime" : [ 6, 55 ],
  "arrivalTime" : [ 12, 0 ],
  "travelTimeMinutes" : 185,
  "aircraft" : "SU9"
}, {
  "from" : "JED",
  "to" : "CMN",
  "airlineDesignator" : "SV",
  "flightNumber" : "377",
  "departureDate" : [ 2022, 1, 1 ],
  "departureTime" : [ 6, 55 ],
  "arrivalTime" : [ 11, 20 ],
  "travelTimeMinutes" : 385,
  "aircraft" : "789"
}, {
  "from" : "JED",
  "to" : "DXB",
  "airlineDesignator" : "SV",
  "flightNumber" : "566",
  "departureDate" : [ 2022, 1, 1 ],
  "departureTime" : [ 6, 55 ],
  "arrivalTime" : [ 10, 45 ],
  "travelTimeMinutes" : 170,
  "aircraft" : "320"
}, {
  "from" : "VCS",
  "to" : "SGN",
  "airlineDesignator" : "VN",
  "flightNumber" : "8064",
  "departureDate" : [ 2022, 1, 1 ],
  "departureTime" : [ 6, 55 ],
  "arrivalTime" : [ 8, 0 ],
  "travelTimeMinutes" : 65,
  "aircraft" : "AT7"
} ]